{
  "hero": [
    {
      "id": "Bhanumati (2025) Season 1 Episode 3 (VooVi Originals)",
      "title": "Bhanumati (2025) Season 1 Episode 3 (VooVi Originals)",
      "poster": "https://m.media-amazon.com/images/M/MV5BZTcyODc4MjctZjRhMy00MDE1LWJjMzYtN2Q4ODM0MjU5ODBjXkEyXkFqcGc@._V1_FMjpg_UY640_.jpg",
      "stream_url": "https://vsyshost.ydc1wes.me/hls2/01/00008/exi4kpa7c3cd_,l,h,.urlset/master.m3u8?t=3HA3T-uEfpyfsLZQWYhBUitN6zqvnws-ts2dsa0-ppE&s=1778094950&e=21600&f=40789&i=0.0&sp=0",
      "headers": {
        "Referer": "https://speedostream1.com/"
      }
    }
  ],
  "categories": [
    {
      "name": "Latest from input1.json",
      "items": [
        {
          "id": "Bhanumati (2025) Season 1 Episode 3 (VooVi Originals)",
          "title": "Bhanumati (2025) Season 1 Episode 3 (VooVi Originals)",
          "poster": "https://m.media-amazon.com/images/M/MV5BZTcyODc4MjctZjRhMy00MDE1LWJjMzYtN2Q4ODM0MjU5ODBjXkEyXkFqcGc@._V1_FMjpg_UY640_.jpg",
          "stream_url": "https://vsyshost.ydc1wes.me/hls2/01/00008/exi4kpa7c3cd_,l,h,.urlset/master.m3u8?t=3HA3T-uEfpyfsLZQWYhBUitN6zqvnws-ts2dsa0-ppE&s=1778094950&e=21600&f=40789&i=0.0&sp=0",
          "headers": {
            "Referer": "https://speedostream1.com/"
          }
        },
        {
          "id": "Bhanumati (2025) Season 1 Episode 2 (VooVi Originals)",
          "title": "Bhanumati (2025) Season 1 Episode 2 (VooVi Originals)",
          "poster": "https://m.media-amazon.com/images/M/MV5BNWU2Y2NjMzMtNTFmMi00YjkxLTliYjItZGU0YjI5NDY3YWIyXkEyXkFqcGc@._V1_FMjpg_UY720_.jpg",
          "stream_url": "https://vsyshost.ydc1wes.me/hls2/01/00008/dp201r4in5ti_,l,h,.urlset/master.m3u8?t=pNna94nN1Y69MPEh8Wm4tqU13XB3jVHCuL7khwMN_Kg&s=1778094952&e=21600&f=40465&i=0.0&sp=0",
          "headers": {
            "Referer": "https://speedostream1.com/"
          }
        },
        {
          "id": "Bhanumati (2025) Season 1 Episode 1 (VooVi Originals)",
          "title": "Bhanumati (2025) Season 1 Episode 1 (VooVi Originals)",
          "poster": "https://m.media-amazon.com/images/M/MV5BZTcyODc4MjctZjRhMy00MDE1LWJjMzYtN2Q4ODM0MjU5ODBjXkEyXkFqcGc@._V1_FMjpg_UY640_.jpg",
          "stream_url": "https://jagur.ydc1wes.me/hls2/01/00008/br9mair7p0ft_,l,h,.urlset/master.m3u8?t=LvPrguGwGDD_-JP45RD5UCzaOJBtKNpC2J7e-K2swDo&s=1778094952&e=21600&f=40099&i=0.0&sp=0",
          "headers": {
            "Referer": "https://speedostream1.com/"
          }
        },
        {
          "id": "Jaan Bujh Kar (2025) Season 3 Episode 2 (VooVi Originals)",
          "title": "Jaan Bujh Kar (2025) Season 3 Episode 2 (VooVi Originals)",
          "poster": "https://ingfree.xyz/ib/DE20qKcacS.jpg",
          "stream_url": "https://vsyshost.ydc1wes.me/hls2/01/00007/ukcus181z20p_,l,h,.urlset/master.m3u8?t=dPmw4sXIpoZypdAft_fH0m3FaAU2xkDV0TvN_uaiXa4&s=1778094953&e=21600&f=39243&i=0.0&sp=0",
          "headers": {
            "Referer": "https://speedostream1.com/"
          }
        },
        {
          "id": "Jaan Bujh Kar (2025) Season 3 Episode 1 (VooVi Originals)",
          "title": "Jaan Bujh Kar (2025) Season 3 Episode 1 (VooVi Originals)",
          "poster": "https://ingfree.xyz/ib/PJ3F7xSt5F.jpg",
          "stream_url": "https://arabic.ydc1wes.me/hls2/02/00007/80avd92dlptc_,l,h,.urlset/master.m3u8?t=Fs7sOaqI-toCMNg--hD-IvBUmMKvFYe8UQ_v5Ap4K5M&s=1778094954&e=21600&f=39120&i=0.0&sp=0",
          "headers": {
            "Referer": "https://speedostream1.com/"
          }
        },
        {
          "id": "Bachelor Party (2024) Season 1 Episode 6 (VooVi Originals)",
          "title": "Bachelor Party (2024) Season 1 Episode 6 (VooVi Originals)",
          "poster": "https://imego.lat/ib/YsIs3rQo23.jpg",
          "stream_url": "https://abella.ydc1wes.me/hls2/02/00007/0bcs3zq31ig3_,l,h,.urlset/master.m3u8?t=isFKNfwtk8Tzkh5Yy7FCtnnhAkZTGh6CAdZDaDWcjFk&s=1778094955&e=21600&f=35491&i=0.0&sp=0",
          "headers": {
            "Referer": "https://speedostream1.com/"
          }
        },
        {
          "id": "Manchala Ashiq (2024) Season 1 Episode 4 (VooVi Originals)",
          "title": "Manchala Ashiq (2024) Season 1 Episode 4 (VooVi Originals)",
          "poster": "https://m.media-amazon.com/images/M/MV5BMjc2M2FiODYtZDU2ZS00OGVjLTg2MDYtOGJkMmM1NWNkNjRjXkEyXkFqcGc@._V1_FMjpg_UY480_.jpg",
          "stream_url": "https://arima.ydc1wes.me/hls2/01/00007/1puy1vq8be5w_,l,h,.urlset/master.m3u8?t=PYFOBfomUFoO01BniRMvcUDhPxkS1elQbvQTLWvXZxY&s=1778094955&e=21600&f=35476&i=0.0&sp=0",
          "headers": {
            "Referer": "https://speedostream1.com/"
          }
        },
        {
          "id": "Manchala Ashiq (2024) Season 1 Episode 3 (VooVi Originals)",
          "title": "Manchala Ashiq (2024) Season 1 Episode 3 (VooVi Originals)",
          "poster": "https://imego.lat/ib/dA0S0nf3Ya.jpg",
          "stream_url": "https://abella.ydc1wes.me/hls2/01/00007/l0kdv4yjk4su_,l,h,.urlset/master.m3u8?t=buzZ_KkeoLAYvE8qb6_s6bswVo4o1fFIA4G3zNCNTYg&s=1778094956&e=21600&f=35417&i=0.0&sp=0",
          "headers": {
            "Referer": "https://speedostream1.com/"
          }
        },
        {
          "id": "Bachelor Party (2024) Season 1 Episode 5 (VooVi Originals)",
          "title": "Bachelor Party (2024) Season 1 Episode 5 (VooVi Originals)",
          "poster": "https://imego.lat/ib/8rtB5xqw4S.jpg",
          "stream_url": "https://tvhow.ydc1wes.me/hls2/02/00007/qym74sxr4ym6_,l,h,.urlset/master.m3u8?t=7GtbxWTxeJUHYu547cncwBC2iGMsnwgl3oRvsWxdwcE&s=1778094957&e=21600&f=35038&i=0.0&sp=0",
          "headers": {
            "Referer": "https://speedostream1.com/"
          }
        },
        {
          "id": "Manchala Ashiq (2024) Season 1 Episode 2 (VooVi Originals)",
          "title": "Manchala Ashiq (2024) Season 1 Episode 2 (VooVi Originals)",
          "poster": "https://imego.lat/ib/bb04CC4tnH.jpg",
          "stream_url": "https://tvhow.ydc1wes.me/hls2/02/00007/ybewgbdmk1ql_,l,h,.urlset/master.m3u8?t=Y2lN1q_VSrfBavwe_z9U8g86iCJCmWQmUULgCLYGfzk&s=1778094957&e=21600&f=35270&i=0.0&sp=0",
          "headers": {
            "Referer": "https://speedostream1.com/"
          }
        },
        {
          "id": "Manchala Ashiq (2024) Season 1 Episode 1 (VooVi Originals)",
          "title": "Manchala Ashiq (2024) Season 1 Episode 1 (VooVi Originals)",
          "poster": "https://m.media-amazon.com/images/M/MV5BZmE5OTJjMmQtNmY2Yi00ZjlmLWFlY2YtMDdlNWMyYTM1NmM2XkEyXkFqcGc@._V1_FMjpg_UX480_.jpg",
          "stream_url": "https://tvhow.ydc1wes.me/hls2/02/00007/1xhpqo18x41q_,l,h,.urlset/master.m3u8?t=aIorX99wdIb8k89Y7hFyJHSlEsp30dOQQHpNfeynmaI&s=1778094958&e=21600&f=35173&i=0.0&sp=0",
          "headers": {
            "Referer": "https://speedostream1.com/"
          }
        },
        {
          "id": "Jaan Bujh Kar (2023) Season 2 Episode 5 (VooVi Originals)",
          "title": "Jaan Bujh Kar (2023) Season 2 Episode 5 (VooVi Originals)",
          "poster": "https://imego.lat/ib/HOUxguXBtO.jpg",
          "stream_url": "https://tvhow.ydc1wes.me/hls2/02/00005/lykhsbyu88jo_,l,h,.urlset/master.m3u8?t=xabrsvcdGJfx0nzNh_nBI07BuHrcZsNQOmEA5sm3Jcs&s=1778094959&e=21600&f=27068&i=0.0&sp=0",
          "headers": {
            "Referer": "https://speedostream1.com/"
          }
        },
        {
          "id": "ShortCut (2023) Season 1 Episode 4 (VooVi Originals)",
          "title": "ShortCut (2023) Season 1 Episode 4 (VooVi Originals)",
          "poster": "https://m.media-amazon.com/images/M/MV5BYzk0ZmJlMDAtOWVjNC00MGYxLWI1NTktNDQyODQxMWU0OWE4XkEyXkFqcGdeQXVyMTY5NTc5MTY2._V1_FMjpg_UY480_.jpg",
          "stream_url": "https://rasoutin.ydc1wes.me/hls2/01/00005/jolp2quynonv_,l,h,.urlset/master.m3u8?t=PHe5TuQhL1PGq2rAABBbQbd3OGRUS7VfRcRxpXD7NsI&s=1778094959&e=21600&f=29197&i=0.0&sp=0",
          "headers": {
            "Referer": "https://speedostream1.com/"
          }
        },
        {
          "id": "Bachelor Party (2024) Season 1 Episode 4 (VooVi Originals)",
          "title": "Bachelor Party (2024) Season 1 Episode 4 (VooVi Originals)",
          "poster": "https://imego.lat/ib/8rtB5xqw4S.jpg",
          "stream_url": "https://arabic.ydc1wes.me/hls2/01/00006/nyt41vffkm91_,l,h,.urlset/master.m3u8?t=MA0yq0TaKKlXHY9bXpW58Sg_dQsPILTf1AHwpOwEojU&s=1778094960&e=21600&f=34953&i=0.0&sp=0",
          "headers": {
            "Referer": "https://speedostream1.com/"
          }
        },
        {
          "id": "Bachelor Party (2024) Season 1 Episode 3 (VooVi Originals)",
          "title": "Bachelor Party (2024) Season 1 Episode 3 (VooVi Originals)",
          "poster": "https://imego.lat/ib/YsIs3rQo23.jpg",
          "stream_url": "https://tvhow.ydc1wes.me/hls2/02/00006/jrn8c668jehm_,l,h,.urlset/master.m3u8?t=pQvLImueIoLreL_CsxtoDh39Pxmm1e-gTK_dDfvVMQ4&s=1778094960&e=21600&f=34906&i=0.0&sp=0",
          "headers": {
            "Referer": "https://speedostream1.com/"
          }
        },
        {
          "id": "Bachelor Party (2024) Season 1 Episode 2 (VooVi Originals)",
          "title": "Bachelor Party (2024) Season 1 Episode 2 (VooVi Originals)",
          "poster": "https://imego.lat/ib/8rtB5xqw4S.jpg",
          "stream_url": "https://tvhow.ydc1wes.me/hls2/02/00006/177y3zn1bzcn_,l,h,.urlset/master.m3u8?t=Eb3uZkIOh70Nz6bs3wxKPYf9Cku6q5ctqFOveWL647s&s=1778094961&e=21600&f=34776&i=0.0&sp=0",
          "headers": {
            "Referer": "https://speedostream1.com/"
          }
        },
        {
          "id": "Bachelor Party (2024) Season 1 Episode 1 (VooVi Originals)",
          "title": "Bachelor Party (2024) Season 1 Episode 1 (VooVi Originals)",
          "poster": "https://imego.lat/ib/YsIs3rQo23.jpg",
          "stream_url": "https://abella.ydc1wes.me/hls2/01/00006/bwril4owpyqk_,l,h,.urlset/master.m3u8?t=N9gUHHPj9ipQmftwEMdLqL2URSOmFTJGG36muhDpYoQ&s=1778094962&e=21600&f=34775&i=0.0&sp=0",
          "headers": {
            "Referer": "https://speedostream1.com/"
          }
        },
        {
          "id": "Mohe Rang De (2024) Season 1 Episode 8 (VooVi Originals)",
          "title": "Mohe Rang De (2024) Season 1 Episode 8 (VooVi Originals)",
          "poster": "https://m.media-amazon.com/images/M/MV5BZWViYmJhMjMtM2NjZC00NTdlLTk1ZjQtZGE0NDZiNDc3ODRiXkEyXkFqcGdeQXVyMTY5NTc5MTY2._V1_FMjpg_UY480_.jpg",
          "stream_url": "https://vsyshost.ydc1wes.me/hls2/01/00006/bq4luiv417x4_,l,h,.urlset/master.m3u8?t=GTvFryzN01NEa5fM-LxeF7DhJ_usmB5KTt9uhJcXatk&s=1778094962&e=21600&f=30213&i=0.0&sp=0",
          "headers": {
            "Referer": "https://speedostream1.com/"
          }
        },
        {
          "id": "Rangeen Kahaniya (2024) Season 1 Episode 3 (VooVi Originals)",
          "title": "Rangeen Kahaniya (2024) Season 1 Episode 3 (VooVi Originals)",
          "poster": "https://m.media-amazon.com/images/M/MV5BNWY2NTU3MjYtOGZjYS00ZjcxLWI1M2UtMDQ1YzBhM2JiMjI2XkEyXkFqcGdeQXVyMTY5NTc5MTY2._V1_FMjpg_UY480_.jpg",
          "stream_url": "https://tvhow.ydc1wes.me/hls2/02/00005/zxhjjq1slyfe_,l,h,.urlset/master.m3u8?t=azcWq5wSYSs53F0rIgXSNgyrWTpOqkmkqH9Dvf4dmKA&s=1778094963&e=21600&f=29588&i=0.0&sp=0",
          "headers": {
            "Referer": "https://speedostream1.com/"
          }
        },
        {
          "id": "Angrezi Akhbar (2024) Season 1 Episode 4 (VooVi Originals)",
          "title": "Angrezi Akhbar (2024) Season 1 Episode 4 (VooVi Originals)",
          "poster": "https://imego.lat/ib/c0gvQONT0e.jpg",
          "stream_url": "https://tvhow.ydc1wes.me/hls2/02/00006/xqagsxeb2p67_,l,h,.urlset/master.m3u8?t=hbnd3G7qTKuVInSoPIf35XZVKK7ZvHSyb0a1JE-flWE&s=1778094963&e=21600&f=34538&i=0.0&sp=0",
          "headers": {
            "Referer": "https://speedostream1.com/"
          }
        },
        {
          "id": "Angrezi Akhbar (2024) Season 1 Episode 3 (VooVi Originals)",
          "title": "Angrezi Akhbar (2024) Season 1 Episode 3 (VooVi Originals)",
          "poster": "https://imego.lat/ib/V56mJx0sCB.jpg",
          "stream_url": "https://tvhow.ydc1wes.me/hls2/02/00006/3j3lz99ctqtx_,l,h,.urlset/master.m3u8?t=-lMXLCqIgL3utz6tC1fupjeC6PtXge-I2rMBqkXH0Ug&s=1778094964&e=21600&f=34537&i=0.0&sp=0",
          "headers": {
            "Referer": "https://speedostream1.com/"
          }
        },
        {
          "id": "Kitab Ka Raaz (2023) Season 1 Episode 4 (VooVi Originals)",
          "title": "Kitab Ka Raaz (2023) Season 1 Episode 4 (VooVi Originals)",
          "poster": "https://imego.lat/ib/QzLNPtG8W3.jpeg",
          "stream_url": "https://aamir.ydc1wes.me/hls2/01/00004/t8wfv2ploj90_,l,h,.urlset/master.m3u8?t=z6prCEJhNtoSOxUSU5XGZu1EXahxsu00CFYo741wvNs&s=1778094965&e=21600&f=22007&i=0.0&sp=0",
          "headers": {
            "Referer": "https://speedostream1.com/"
          }
        },
        {
          "id": "Sajan Chale Sasural (2024) Season 1 Episode 4 (VooVi Originals)",
          "title": "Sajan Chale Sasural (2024) Season 1 Episode 4 (VooVi Originals)",
          "poster": "https://imego.lat/ib/OtDspAvW2U.jpg",
          "stream_url": "https://arima.ydc1wes.me/hls2/01/00006/dl1zmfzg41tm_,l,h,.urlset/master.m3u8?t=4zUCTbQ5TWeOooUtYHGA3gv2JpyhCnQVZE6BboeLSKw&s=1778094965&e=21600&f=33185&i=0.0&sp=0",
          "headers": {
            "Referer": "https://speedostream1.com/"
          }
        },
        {
          "id": "Sajan Chale Sasural (2024) Season 1 Episode 3 (VooVi Originals)",
          "title": "Sajan Chale Sasural (2024) Season 1 Episode 3 (VooVi Originals)",
          "poster": "https://imego.lat/ib/pCBs7EslQk.jpg",
          "stream_url": "https://arabic.ydc1wes.me/hls2/01/00006/z48ksyoiwe8x_,l,h,.urlset/master.m3u8?t=ouFSRWE1BHoJxHI0gyTePH8DT07ykBr2Wj78VN86wwA&s=1778094966&e=21600&f=33184&i=0.0&sp=0",
          "headers": {
            "Referer": "https://speedostream1.com/"
          }
        },
        {
          "id": "Sajan Chale Sasural (2024) Season 1 Episode 2 (VooVi Originals)",
          "title": "Sajan Chale Sasural (2024) Season 1 Episode 2 (VooVi Originals)",
          "poster": "https://imego.lat/ib/9NrZjFolWd.jpg",
          "stream_url": "https://ritchie.ydc1wes.me/hls2/01/00006/rjd3kfryuram_,l,h,.urlset/master.m3u8?t=rpFC9ie9JRgqY_qT6b-1WgKxkr5H6pviL-dfFXtd6zM&s=1778094966&e=21600&f=33108&i=0.0&sp=0",
          "headers": {
            "Referer": "https://speedostream1.com/"
          }
        },
        {
          "id": "Sajan Chale Sasural (2024) Season 1 Episode 1 (VooVi Originals)",
          "title": "Sajan Chale Sasural (2024) Season 1 Episode 1 (VooVi Originals)",
          "poster": "https://imego.lat/ib/Qs5fcZOXsq.jpg",
          "stream_url": "https://ritchie.ydc1wes.me/hls2/01/00006/09nljw8r9wzy_,l,h,.urlset/master.m3u8?t=FHyd5MgoJeG-bolIb6s3Z0nOVzpJcZnx-g2LT3hInBw&s=1778094967&e=21600&f=33048&i=0.0&sp=0",
          "headers": {
            "Referer": "https://speedostream1.com/"
          }
        },
        {
          "id": "Nehlee Par Dehla (2023) Season 1 Episode 6 (VooVi Originals)",
          "title": "Nehlee Par Dehla (2023) Season 1 Episode 6 (VooVi Originals)",
          "poster": "https://imego.lat/ib/cflx8eMSCc.jpg",
          "stream_url": "https://arabic.ydc1wes.me/hls2/02/00006/q12w6n7vpw77_,l,h,.urlset/master.m3u8?t=7EoyrVSYpusFEeDL7byAV78ih9I7jZUkp96wLdtlk90&s=1778094968&e=21600&f=32399&i=0.0&sp=0",
          "headers": {
            "Referer": "https://speedostream1.com/"
          }
        },
        {
          "id": "Mohe Rang De (2024) Season 1 Episode 7 (VooVi Originals)",
          "title": "Mohe Rang De (2024) Season 1 Episode 7 (VooVi Originals)",
          "poster": "https://m.media-amazon.com/images/M/MV5BYTgwYTg3NjktYjE1Zi00OTFlLWI3NGUtOGRhZjEzMmE4NDc3XkEyXkFqcGdeQXVyMTY5NTc5MTY2._V1_FMjpg_UY576_.jpg",
          "stream_url": "https://vsyshost.ydc1wes.me/hls2/01/00006/krnle3nq7y56_,l,h,.urlset/master.m3u8?t=jijLvB0bgEVHmfJE_onQS3tUGyUi5QaXRYjDZWd6ihk&s=1778094969&e=21600&f=30215&i=0.0&sp=0",
          "headers": {
            "Referer": "https://speedostream1.com/"
          }
        },
        {
          "id": "Godaniya (2023) Season 1 Episode 4 (VooVi Originals)",
          "title": "Godaniya (2023) Season 1 Episode 4 (VooVi Originals)",
          "poster": "https://m.media-amazon.com/images/M/MV5BZmNhNzY2OTYtNGYyNC00OWJiLThkYzgtNTQ3MzEwNDU2NDY2XkEyXkFqcGdeQXVyMTY5NTc5MTY2._V1_FMjpg_UY480_.jpg",
          "stream_url": "https://oldfils.ydc1wes.me/hls2/01/00005/kk4wth39c7kt_,l,h,.urlset/master.m3u8?t=xXx0sBzBHkjBod6rOEeU8c1YhOHfTqkpP_00g0X2xkw&s=1778094969&e=21600&f=29193&i=0.0&sp=0",
          "headers": {
            "Referer": "https://speedostream1.com/"
          }
        },
        {
          "id": "Angrezi Akhbar (2024) Season 1 Episode 2 (VooVi Originals)",
          "title": "Angrezi Akhbar (2024) Season 1 Episode 2 (VooVi Originals)",
          "poster": "https://m.media-amazon.com/images/M/MV5BMjcxOTJlY2MtNWU1Zi00M2I5LTlkY2EtOWE5NmI3YzNkN2JlXkEyXkFqcGdeQXVyMTY5NTc5MTY2._V1_FMjpg_UY480_.jpg",
          "stream_url": "https://vsyshost.ydc1wes.me/hls2/01/00006/5ua4at9snbfp_,l,h,.urlset/master.m3u8?t=tbUAODjzTKAsHNApmS_LDRe6bab7s2RnaAC4ediFpZQ&s=1778094970&e=21600&f=30404&i=0.0&sp=0",
          "headers": {
            "Referer": "https://speedostream1.com/"
          }
        },
        {
          "id": "Angrezy Akhbar (2024) Season 1 Episode 1 (VooVi Originals)",
          "title": "Angrezy Akhbar (2024) Season 1 Episode 1 (VooVi Originals)",
          "poster": "https://imego.lat/ib/eXhuQhrNqT.jpg",
          "stream_url": "https://vsyshost.ydc1wes.me/hls2/01/00006/dmruk8nprs7j_,l,h,.urlset/master.m3u8?t=4nJNYVbBKE-jiks84hVtjq5sIaGsaJ4dmb3zVpzTjAs&s=1778094970&e=21600&f=30358&i=0.0&sp=0",
          "headers": {
            "Referer": "https://speedostream1.com/"
          }
        },
        {
          "id": "Mohe Rang De (2024) Season 1 Episode 6 (VooVi Originals)",
          "title": "Mohe Rang De (2024) Season 1 Episode 6 (VooVi Originals)",
          "poster": "https://m.media-amazon.com/images/M/MV5BMTFlZTdmMjYtZTc5Mi00NjA1LTg1YjYtMjVkNjAyMTczMTIwXkEyXkFqcGdeQXVyMTY5NTc5MTY2._V1_FMjpg_UX480_.jpg",
          "stream_url": "https://vsyshost.ydc1wes.me/hls2/01/00006/4bezmzrqavrg_,l,h,.urlset/master.m3u8?t=jsX5GjuEOqAl0LXk0cjgev3S9vaZAVgxyy3ctStcom8&s=1778094971&e=21600&f=30343&i=0.0&sp=0",
          "headers": {
            "Referer": "https://speedostream1.com/"
          }
        },
        {
          "id": "Mohe Rang De (2024) Season 1 Episode 5 (VooVi Originals)",
          "title": "Mohe Rang De (2024) Season 1 Episode 5 (VooVi Originals)",
          "poster": "https://m.media-amazon.com/images/M/MV5BZWNmZDNlYTctZTc4Yi00NzQ4LTkzNzQtMTA2Yzk4MzUyYzUxXkEyXkFqcGdeQXVyMTY5NTc5MTY2._V1_FMjpg_UX480_.jpg",
          "stream_url": "https://vsyshost.ydc1wes.me/hls2/01/00006/ls6acra8wczq_,l,h,.urlset/master.m3u8?t=thrL_bqOViVU41tAjLKVxMv7157MIqokx3s_jEaeKco&s=1778094972&e=21600&f=30246&i=0.0&sp=0",
          "headers": {
            "Referer": "https://speedostream1.com/"
          }
        },
        {
          "id": "ShortCut (2023) Season 1 Episode 6 (VooVi Originals)",
          "title": "ShortCut (2023) Season 1 Episode 6 (VooVi Originals)",
          "poster": "https://m.media-amazon.com/images/M/MV5BZDEzNjljOWUtMDU3OC00NDk1LTliMjgtODQwY2E5MjlhYTViXkEyXkFqcGdeQXVyMTY5NTc5MTY2._V1_FMjpg_UY480_.jpg",
          "stream_url": "https://jnaove.ydc1wes.me/hls2/02/00005/2o5cxhk2njgf_,l,h,.urlset/master.m3u8?t=lefqmS5c0PBJlwtZgPom_wwrafJD3UE1eRMMMHqhuDo&s=1778094972&e=21600&f=28958&i=0.0&sp=0",
          "headers": {
            "Referer": "https://speedostream1.com/"
          }
        },
        {
          "id": "Mohe Rang De (2024) Season 1 Episode 4 (VooVi Originals)",
          "title": "Mohe Rang De (2024) Season 1 Episode 4 (VooVi Originals)",
          "poster": "https://m.media-amazon.com/images/M/MV5BZWViYmJhMjMtM2NjZC00NTdlLTk1ZjQtZGE0NDZiNDc3ODRiXkEyXkFqcGdeQXVyMTY5NTc5MTY2._V1_FMjpg_UY480_.jpg",
          "stream_url": "https://vsyshost.ydc1wes.me/hls2/01/00006/wjlf6sbhz8rs_,l,h,.urlset/master.m3u8?t=KxUO7igXqcXdQuL2wh-Jz3Qr4tYFwxUJk-g3WObMgTQ&s=1778094973&e=21600&f=30000&i=0.0&sp=0",
          "headers": {
            "Referer": "https://speedostream1.com/"
          }
        },
        {
          "id": "ShortCut (2023) Season 1 Episode 5 (VooVi Originals)",
          "title": "ShortCut (2023) Season 1 Episode 5 (VooVi Originals)",
          "poster": "https://m.media-amazon.com/images/M/MV5BZGQ3NmJlNjYtYjJkNi00MDEyLThhZTgtOTQ1MjgyMmQwODNjXkEyXkFqcGdeQXVyMTY5NTc5MTY2._V1_FMjpg_UY480_.jpg",
          "stream_url": "https://jnaove.ydc1wes.me/hls2/02/00005/kderxkcanmg2_,l,h,.urlset/master.m3u8?t=Lp1-mtWGKK9zpB6obsE37j5RSNLFKWzRhwxNCi3IUx8&s=1778094973&e=21600&f=28957&i=0.0&sp=0",
          "headers": {
            "Referer": "https://speedostream1.com/"
          }
        },
        {
          "id": "Mohe Rang De (2024) Season 1 Episode 3 (VooVi Originals)",
          "title": "Mohe Rang De (2024) Season 1 Episode 3 (VooVi Originals)",
          "poster": "https://m.media-amazon.com/images/M/MV5BYzdkNzVlYzMtODZlYy00MWFkLThmMzctNmFmZDBlOTljNzZjXkEyXkFqcGdeQXVyMTY5NTc5MTY2._V1_FMjpg_UY480_.jpg",
          "stream_url": "https://arabic.ydc1wes.me/hls2/02/00006/pp573908c9jx_,l,h,.urlset/master.m3u8?t=vrRjTC3UuFsBZwwrQ7VrsXBiL0_BV8LpPeHqPIlwUc0&s=1778094974&e=21600&f=30001&i=0.0&sp=0",
          "headers": {
            "Referer": "https://speedostream1.com/"
          }
        },
        {
          "id": "Mohe Rang De (2024) Season 1 Episode 2 (VooVi Originals)",
          "title": "Mohe Rang De (2024) Season 1 Episode 2 (VooVi Originals)",
          "poster": "https://m.media-amazon.com/images/M/MV5BZWViYmJhMjMtM2NjZC00NTdlLTk1ZjQtZGE0NDZiNDc3ODRiXkEyXkFqcGdeQXVyMTY5NTc5MTY2._V1_FMjpg_UY480_.jpg",
          "stream_url": "https://tvhow.ydc1wes.me/hls2/02/00005/xrs4pxd3pq7g_,l,h,.urlset/master.m3u8?t=PbKkiq1jck3H-hqFQQDoxBnilnmLph1rIOVzp4X51YY&s=1778094975&e=21600&f=29785&i=0.0&sp=0",
          "headers": {
            "Referer": "https://speedostream1.com/"
          }
        },
        {
          "id": "Mohe Rang De (2024) Season 1 Episode 1 (VooVi Originals)",
          "title": "Mohe Rang De (2024) Season 1 Episode 1 (VooVi Originals)",
          "poster": "https://m.media-amazon.com/images/M/MV5BYzdkNzVlYzMtODZlYy00MWFkLThmMzctNmFmZDBlOTljNzZjXkEyXkFqcGdeQXVyMTY5NTc5MTY2._V1_FMjpg_UY480_.jpg",
          "stream_url": "https://tvhow.ydc1wes.me/hls2/02/00005/oo7sgaa30io0_,l,h,.urlset/master.m3u8?t=5qd9Gy4hSOK0vKHAD_JjErt8lWHcTiMVDlAeCTb9XSY&s=1778094975&e=21600&f=29784&i=0.0&sp=0",
          "headers": {
            "Referer": "https://speedostream1.com/"
          }
        },
        {
          "id": "Rangeen Kahaniya (2024) Season 1 Episode 4 (VooVi Originals)",
          "title": "Rangeen Kahaniya (2024) Season 1 Episode 4 (VooVi Originals)",
          "poster": "https://m.media-amazon.com/images/M/MV5BNGFhMDNhMzYtY2NlOS00OTdkLTk0NDYtMmY0MDYwOWM5ODZhXkEyXkFqcGdeQXVyMTY5NTc5MTY2._V1_FMjpg_UY480_.jpg",
          "stream_url": "https://tvhow.ydc1wes.me/hls2/02/00005/1cdespnwmycm_,l,h,.urlset/master.m3u8?t=xxdN87_aK1v8jN7mshCxi3dORr9KYUtW4gPgJp-NLOE&s=1778094976&e=21600&f=29693&i=0.0&sp=0",
          "headers": {
            "Referer": "https://speedostream1.com/"
          }
        },
        {
          "id": "Rangeen Kahaniya (2024) Season 1 Episode 2 (VooVi Originals)",
          "title": "Rangeen Kahaniya (2024) Season 1 Episode 2 (VooVi Originals)",
          "poster": "https://m.media-amazon.com/images/M/MV5BMTM3YzY4YjktZmFmZS00ZmE4LWJjNGYtYzQ5NjRkNGMzMmI0XkEyXkFqcGdeQXVyMTY5NTc5MTY2._V1_FMjpg_UY600_.jpg",
          "stream_url": "https://arabic.ydc1wes.me/hls2/02/00005/1hrb3ug3hv82_,l,h,.urlset/master.m3u8?t=YTScLQJO2YjYRK65Fym4W52XAZ5_D8q9wMvp0fOVmOY&s=1778094976&e=21600&f=29489&i=0.0&sp=0",
          "headers": {
            "Referer": "https://speedostream1.com/"
          }
        },
        {
          "id": "Rangeen Kahaniya (2024) Season 1 Episode 1 (VooVi Originals)",
          "title": "Rangeen Kahaniya (2024) Season 1 Episode 1 (VooVi Originals)",
          "poster": "https://m.media-amazon.com/images/M/MV5BMTM3YzY4YjktZmFmZS00ZmE4LWJjNGYtYzQ5NjRkNGMzMmI0XkEyXkFqcGdeQXVyMTY5NTc5MTY2._V1_FMjpg_UY600_.jpg",
          "stream_url": "https://oldfils.ydc1wes.me/hls2/01/00005/j5b2qyghlag1_,l,h,.urlset/master.m3u8?t=jpWK-KGJNWjkD0MfTtUeSMw3DGOZP-r06ufsPy0XcEE&s=1778094977&e=21600&f=29418&i=0.0&sp=0",
          "headers": {
            "Referer": "https://speedostream1.com/"
          }
        },
        {
          "id": "Godaniya (2023) Season 1 Episode 3 (VooVi Originals)",
          "title": "Godaniya (2023) Season 1 Episode 3 (VooVi Originals)",
          "poster": "https://m.media-amazon.com/images/M/MV5BYWQyZGQyMmItNjJhYi00OWMxLWExYjEtYjc3YTI2ZjM3ZDRmXkEyXkFqcGdeQXVyMTY5NTc5MTY2._V1_FMjpg_UY480_.jpg",
          "stream_url": "https://cubbi.ydc1wes.me/hls2/04/00005/cr9y035ciw5i_,l,h,.urlset/master.m3u8?t=pMcRDJxP50MjFf0BKcEmBF5IcoVCzmppR0cE_4Aalkg&s=1778094978&e=21600&f=29192&i=0.0&sp=0",
          "headers": {
            "Referer": "https://speedostream1.com/"
          }
        },
        {
          "id": "ShortCut (2023) Season 1 Episode 3 (VooVi Originals)",
          "title": "ShortCut (2023) Season 1 Episode 3 (VooVi Originals)",
          "poster": "https://m.media-amazon.com/images/M/MV5BZGQ3NmJlNjYtYjJkNi00MDEyLThhZTgtOTQ1MjgyMmQwODNjXkEyXkFqcGdeQXVyMTY5NTc5MTY2._V1_FMjpg_UY480_.jpg",
          "stream_url": "https://rasoutin.ydc1wes.me/hls2/01/00005/0xremmfajf7p_,l,h,.urlset/master.m3u8?t=1snBK51amsfAtzyJVUUJAzPNk5vzbblNKRMNF7Ocn4E&s=1778094978&e=21600&f=29126&i=0.0&sp=0",
          "headers": {
            "Referer": "https://speedostream1.com/"
          }
        },
        {
          "id": "Godaniya (2023) Season 1 Episode 2 (VooVi Originals)",
          "title": "Godaniya (2023) Season 1 Episode 2 (VooVi Originals)",
          "poster": "https://m.media-amazon.com/images/M/MV5BMDI3ZGI4OTQtM2NmOC00YTNhLWIzMGMtYzIyZWZjNzE2ZWNjXkEyXkFqcGdeQXVyMTY5NTc5MTY2._V1_FMjpg_UY480_.jpg",
          "stream_url": "https://arima.ydc1wes.me/hls2/01/00005/hrr4h31sswal_,l,h,.urlset/master.m3u8?t=xm6rrCz1FDoSsf47Em1BLTsMSjHDwjoUdSZ1wO8ckg0&s=1778094979&e=21600&f=29037&i=0.0&sp=0",
          "headers": {
            "Referer": "https://speedostream1.com/"
          }
        },
        {
          "id": "Godaniya (2023) Season 1 Episode 1 (VooVi Originals)",
          "title": "Godaniya (2023) Season 1 Episode 1 (VooVi Originals)",
          "poster": "https://imego.lat/ib/cTaz8QFFj2.jpg",
          "stream_url": "https://jnaove.ydc1wes.me/hls2/02/00005/8xq9tminb2cq_,l,h,.urlset/master.m3u8?t=hTcfnrFBjgeodwKvh8bxwIfwJRvzDGoXu_RwEcHgM0c&s=1778094979&e=21600&f=29036&i=0.0&sp=0",
          "headers": {
            "Referer": "https://speedostream1.com/"
          }
        },
        {
          "id": "Mona 69 (2023) Season 1 Episode 6 (VooVi Originals)",
          "title": "Mona 69 (2023) Season 1 Episode 6 (VooVi Originals)",
          "poster": "https://m.media-amazon.com/images/M/MV5BYTNkNDc2N2MtNGFjZC00M2ZmLTgyYWYtZWVhOGUxYzA2NzAyXkEyXkFqcGdeQXVyMTI4MTk2NzMz._V1_FMjpg_UY480_.jpg",
          "stream_url": "https://arabic.ydc1wes.me/hls2/02/00005/zr7qvp4v5lts_,l,h,.urlset/master.m3u8?t=u3VyIJe-qYXvdystimcsbwQRTx-E_AC0lu2XkEvhiEI&s=1778094980&e=21600&f=25794&i=0.0&sp=0",
          "headers": {
            "Referer": "https://speedostream1.com/"
          }
        },
        {
          "id": "ShortCut (2023) Season 1 Episode 2 (VooVi Originals)",
          "title": "ShortCut (2023) Season 1 Episode 2 (VooVi Originals)",
          "poster": "https://imego.lat/ib/Napiw5ZtDW.jpg",
          "stream_url": "https://aamir.ydc1wes.me/hls2/01/00005/0uggh879nkrk_,l,h,.urlset/master.m3u8?t=VG9b17WbYmZXnoO4OYP7mJedtfzZYhFRP1yNzMShIos&s=1778094981&e=21600&f=28799&i=0.0&sp=0",
          "headers": {
            "Referer": "https://speedostream1.com/"
          }
        },
        {
          "id": "ShortCut (2023) Season 1 Episode 1 (VooVi Originals)",
          "title": "ShortCut (2023) Season 1 Episode 1 (VooVi Originals)",
          "poster": "https://imego.lat/ib/Napiw5ZtDW.jpg",
          "stream_url": "https://aamir.ydc1wes.me/hls2/01/00005/4h4rujq6hqvi_,l,h,.urlset/master.m3u8?t=XwDIZF7diUoZ-TZI6Ks13J0wkDbOcTMCrMCWah1nCaE&s=1778094981&e=21600&f=28798&i=0.0&sp=0",
          "headers": {
            "Referer": "https://speedostream1.com/"
          }
        },
        {
          "id": "Nathuniya (2023) Season 1 Episode 6 (VooVi Originals)",
          "title": "Nathuniya (2023) Season 1 Episode 6 (VooVi Originals)",
          "poster": "https://m.media-amazon.com/images/M/MV5BMjZhMzUzMTYtZGQwNi00YmIxLTk2NjAtZmYzNDJmNzQxNWFmXkEyXkFqcGdeQXVyMTY5NTc5MTY2._V1_FMjpg_UX389_.jpg",
          "stream_url": "https://jnaove.ydc1wes.me/hls2/02/00005/4r5566x7ii3d_,l,h,.urlset/master.m3u8?t=Fy7QGZW-0pW2kwMX3o8lAT60zdiLIsY1lhpb7-6mDLE&s=1778094982&e=21600&f=28572&i=0.0&sp=0",
          "headers": {
            "Referer": "https://speedostream1.com/"
          }
        },
        {
          "id": "Imli Bhabhi (2023) Season 1 Episode 6 (VooVi Originals)",
          "title": "Imli Bhabhi (2023) Season 1 Episode 6 (VooVi Originals)",
          "poster": "https://m.media-amazon.com/images/M/MV5BNDNlOGRiNjEtNTZlMC00ZjEyLWI4NTgtYjNjNzQ4M2YxNmI5XkEyXkFqcGdeQXVyMTY5NTc5MTY2._V1_FMjpg_UY480_.jpg",
          "stream_url": "https://aamir.ydc1wes.me/hls2/01/00005/ny6die6sb0ru_,l,h,.urlset/master.m3u8?t=lGCM_jIfgxhWFRjZk0sRuQ6Ax7VY2arwWDeb_QkxhmA&s=1778094983&e=21600&f=28731&i=0.0&sp=0",
          "headers": {
            "Referer": "https://speedostream1.com/"
          }
        },
        {
          "id": "Imli Bhabhi (2023) Season 1 Episode 5 (VooVi Originals)",
          "title": "Imli Bhabhi (2023) Season 1 Episode 5 (VooVi Originals)",
          "poster": "https://m.media-amazon.com/images/M/MV5BOTVlOGI5NDctYTQ0My00N2JkLWE1MjUtOTJjZTA5MzA1YTAzXkEyXkFqcGdeQXVyMTY5NTc5MTY2._V1_FMjpg_UY617_.jpg",
          "stream_url": "https://aamir.ydc1wes.me/hls2/01/00005/f8tbypbqatel_,l,h,.urlset/master.m3u8?t=Fa2YzupreeaqVbkbDBXcVzVeumJuCs4NXEg-9_t7x9k&s=1778094983&e=21600&f=28687&i=0.0&sp=0",
          "headers": {
            "Referer": "https://speedostream1.com/"
          }
        },
        {
          "id": "Nathuniya (2023) Season 1 Episode 5 (VooVi Originals)",
          "title": "Nathuniya (2023) Season 1 Episode 5 (VooVi Originals)",
          "poster": "https://m.media-amazon.com/images/M/MV5BYmFhMzgyMTEtMWUxMS00Y2FkLTk1MDgtMzMyODU1MTNiNjQ0XkEyXkFqcGdeQXVyMTY5NTc5MTY2._V1_FMjpg_UY480_.jpg",
          "stream_url": "https://jnaove.ydc1wes.me/hls2/02/00005/jj2pgvuzo47o_,l,h,.urlset/master.m3u8?t=vThGqGMyBuplhWUs2k05cR_DVsULwB2EI59azEAhv_g&s=1778094984&e=21600&f=28571&i=0.0&sp=0",
          "headers": {
            "Referer": "https://speedostream1.com/"
          }
        },
        {
          "id": "Berang (2023) Season 1 Episode 1 (VooVi Originals)",
          "title": "Berang (2023) Season 1 Episode 1 (VooVi Originals)",
          "poster": "https://imego.lat/ib/wMaPjJcOR6.jpg",
          "stream_url": "https://aamir.ydc1wes.me/hls2/01/00005/y5z9artgm6es_,l,h,.urlset/master.m3u8?t=oT4_WKT5WcuJmyhUKlXMOpquXRcsgl--zc2iTJEy_eo&s=1778094984&e=21600&f=28490&i=0.0&sp=0",
          "headers": {
            "Referer": "https://speedostream1.com/"
          }
        },
        {
          "id": "Jaan Bujh Kar (2023) Season 2 Episode 4 (VooVi Originals)",
          "title": "Jaan Bujh Kar (2023) Season 2 Episode 4 (VooVi Originals)",
          "poster": "https://imego.lat/ib/w9AZ1IB6Th.png",
          "stream_url": "https://aamir.ydc1wes.me/hls2/01/00005/p22jonsltk3k_,l,h,.urlset/master.m3u8?t=vx6zW6tA7Zg3Y8uQnxsxLleMR5WB1_JwxJ22KaE-JoY&s=1778094985&e=21600&f=27066&i=0.0&sp=0",
          "headers": {
            "Referer": "https://speedostream1.com/"
          }
        },
        {
          "id": "Jaan Bujh Kar (2023) Season 2 Episode 3 (VooVi Originals)",
          "title": "Jaan Bujh Kar (2023) Season 2 Episode 3 (VooVi Originals)",
          "poster": "https://imego.lat/ib/w9AZ1IB6Th.png",
          "stream_url": "https://aamir.ydc1wes.me/hls2/01/00005/1hf6fx0g96cy_,l,h,.urlset/master.m3u8?t=HYYFrfAF75kTJhpb4lMnZO3g9ku-FEZWZyUC4xxmG0o&s=1778094985&e=21600&f=27067&i=0.0&sp=0",
          "headers": {
            "Referer": "https://speedostream1.com/"
          }
        },
        {
          "id": "Nathuniya (2023) Season 1 Episode 4 (VooVi Originals)",
          "title": "Nathuniya (2023) Season 1 Episode 4 (VooVi Originals)",
          "poster": "https://imego.lat/ib/b8UEogfaek.jpg",
          "stream_url": "https://jnaove.ydc1wes.me/hls2/02/00005/ht6z0ekinwki_,l,h,.urlset/master.m3u8?t=LrI1blFdEUQ32siZuVBkqx8a8e8hv5ZGXDJmROEctPI&s=1778094986&e=21600&f=28127&i=0.0&sp=0",
          "headers": {
            "Referer": "https://speedostream1.com/"
          }
        },
        {
          "id": "Nathuniya (2023) Season 1 Episode 3 (VooVi Originals)",
          "title": "Nathuniya (2023) Season 1 Episode 3 (VooVi Originals)",
          "poster": "https://imego.lat/ib/b8UEogfaek.jpg",
          "stream_url": "https://aamir.ydc1wes.me/hls2/01/00005/09ftas9i0zji_,l,h,.urlset/master.m3u8?t=qW1KsRqA9jLJakKr3PN20GYxxj2IH_RmI6LRPjDgYL8&s=1778094987&e=21600&f=28126&i=0.0&sp=0",
          "headers": {
            "Referer": "https://speedostream1.com/"
          }
        },
        {
          "id": "Nathuniya (2023) Season 1 Episode 2 (VooVi Originals)",
          "title": "Nathuniya (2023) Season 1 Episode 2 (VooVi Originals)",
          "poster": "https://imego.lat/ib/scQ6gSokZ5.jpg",
          "stream_url": "https://aamir.ydc1wes.me/hls2/01/00005/x6za77fwkwgw_,l,h,.urlset/master.m3u8?t=WBQDm-fzqNo0Snk5WtKfHmqNJwp5S5APjoQMMz5H3ds&s=1778094987&e=21600&f=27984&i=0.0&sp=0",
          "headers": {
            "Referer": "https://speedostream1.com/"
          }
        },
        {
          "id": "Nathuniya (2023) Season 1 Episode 1 (VooVi Originals)",
          "title": "Nathuniya (2023) Season 1 Episode 1 (VooVi Originals)",
          "poster": "https://imego.lat/ib/scQ6gSokZ5.jpg",
          "stream_url": "https://aamir.ydc1wes.me/hls2/01/00005/5ctvbgx18ya4_,l,h,.urlset/master.m3u8?t=EtNFI4vVI-vtcC1ERhcEIeXJRlN1u1HJtPiaJU8XWqs&s=1778094988&e=21600&f=27992&i=0.0&sp=0",
          "headers": {
            "Referer": "https://speedostream1.com/"
          }
        },
        {
          "id": "Nehlee Par Dehla (2023) Season 1 Episode 5 (VooVi Originals)",
          "title": "Nehlee Par Dehla (2023) Season 1 Episode 5 (VooVi Originals)",
          "poster": "https://m.media-amazon.com/images/M/MV5BYmQ3YTU2M2UtMGZmYS00Y2Y4LWJiZGQtNmUyZWY2MmQ1Y2ViXkEyXkFqcGdeQXVyMTI4MTk2NzMz._V1_FMjpg_UY480_.jpg",
          "stream_url": "https://jnaove.ydc1wes.me/hls2/01/00005/kokgsgh3dd0k_,l,h,.urlset/master.m3u8?t=46fYffMTNp1QIh3rLbsFJU1dHqHcz1Y5xXkofgx9ilQ&s=1778094988&e=21600&f=26572&i=0.0&sp=0",
          "headers": {
            "Referer": "https://speedostream1.com/"
          }
        },
        {
          "id": "Jaan Bujh Kar (2023) Season 2 Episode 2 (VooVi Originals)",
          "title": "Jaan Bujh Kar (2023) Season 2 Episode 2 (VooVi Originals)",
          "poster": "https://imego.lat/ib/HOUxguXBtO.jpg",
          "stream_url": "https://aamir.ydc1wes.me/hls2/01/00005/9mgzkgjivx8j_,l,h,.urlset/master.m3u8?t=s_a6lg10o_6mLS08IzgiQMh4B_eRic943TID2kc9VHA&s=1778094989&e=21600&f=27915&i=0.0&sp=0",
          "headers": {
            "Referer": "https://speedostream1.com/"
          }
        },
        {
          "id": "Imli Bhabhi (2023) Season 1 Episode 4 (VooVi Originals)",
          "title": "Imli Bhabhi (2023) Season 1 Episode 4 (VooVi Originals)",
          "poster": "https://m.media-amazon.com/images/M/MV5BODk3NWE0ZTgtNGQyZi00OTJiLWI4YTYtYjMyOGU4ZDU5ZGNlXkEyXkFqcGdeQXVyMTY5NTc5MTY2._V1_FMjpg_UY617_.jpg",
          "stream_url": "https://aamir.ydc1wes.me/hls2/01/00005/97s4tpwqiyn5_,l,h,.urlset/master.m3u8?t=pazXDFXD0-V4ZOTgk5Pwr6RhXlkIwlCRkwxkXDLhn9Q&s=1778094990&e=21600&f=27836&i=0.0&sp=0",
          "headers": {
            "Referer": "https://speedostream1.com/"
          }
        },
        {
          "id": "Imli Bhabhi (2023) Season 1 Episode 3 (VooVi Originals)",
          "title": "Imli Bhabhi (2023) Season 1 Episode 3 (VooVi Originals)",
          "poster": "https://m.media-amazon.com/images/M/MV5BODk3NWE0ZTgtNGQyZi00OTJiLWI4YTYtYjMyOGU4ZDU5ZGNlXkEyXkFqcGdeQXVyMTY5NTc5MTY2._V1_FMjpg_UY617_.jpg",
          "stream_url": "https://aamir.ydc1wes.me/hls2/01/00005/tqy07kq7ca6l_,l,h,.urlset/master.m3u8?t=SS-n9aCxXq21JBmB09ETtPjM3q1DAFCR4TO0Nsllwc0&s=1778094990&e=21600&f=27835&i=0.0&sp=0",
          "headers": {
            "Referer": "https://speedostream1.com/"
          }
        },
        {
          "id": "Imli Bhabhi (2023) Season 1 Episode 2 (VooVi Originals)",
          "title": "Imli Bhabhi (2023) Season 1 Episode 2 (VooVi Originals)",
          "poster": "https://m.media-amazon.com/images/M/MV5BNDNlOGRiNjEtNTZlMC00ZjEyLWI4NTgtYjNjNzQ4M2YxNmI5XkEyXkFqcGdeQXVyMTY5NTc5MTY2._V1_FMjpg_UY480_.jpg",
          "stream_url": "https://aamir.ydc1wes.me/hls2/01/00005/9cufiiyq6z8a_,l,h,.urlset/master.m3u8?t=9XbZRSE-mXrTTCSJVVfm_q1RZDwSDbCEHIqi0zKRiN8&s=1778094991&e=21600&f=27628&i=0.0&sp=0",
          "headers": {
            "Referer": "https://speedostream1.com/"
          }
        },
        {
          "id": "Imli Bhabhi (2023) Season 1 Episode 1 (VooVi Originals)",
          "title": "Imli Bhabhi (2023) Season 1 Episode 1 (VooVi Originals)",
          "poster": "https://m.media-amazon.com/images/M/MV5BOTVlOGI5NDctYTQ0My00N2JkLWE1MjUtOTJjZTA5MzA1YTAzXkEyXkFqcGdeQXVyMTY5NTc5MTY2._V1_FMjpg_UY617_.jpg",
          "stream_url": "https://aamir.ydc1wes.me/hls2/01/00005/9fkp00mhgbkj_,l,h,.urlset/master.m3u8?t=E2ZGgNzm7_8API4laIcyTn2b1f6NO-P4WK_mAtkA594&s=1778094992&e=21600&f=27627&i=0.0&sp=0",
          "headers": {
            "Referer": "https://speedostream1.com/"
          }
        },
        {
          "id": "X Class (2023) Season 1 Part 3 (VooVi Originals)",
          "title": "X Class (2023) Season 1 Part 3 (VooVi Originals)",
          "poster": "https://imego.lat/ib/I3ct1s3U1O.jpg",
          "stream_url": "https://aamir.ydc1wes.me/hls2/01/00005/gseq572acboy_,l,h,.urlset/master.m3u8?t=eCc6ugDUVj1d0mx3IfkBQgwiWz8IN9uuqWi7TywpvZw&s=1778094993&e=21600&f=27442&i=0.0&sp=0",
          "headers": {
            "Referer": "https://speedostream1.com/"
          }
        },
        {
          "id": "Nehlee Par Dehla (2023) Season 1 Episode 4 (VooVi Originals)",
          "title": "Nehlee Par Dehla (2023) Season 1 Episode 4 (VooVi Originals)",
          "poster": "https://m.media-amazon.com/images/M/MV5BYmQ3YTU2M2UtMGZmYS00Y2Y4LWJiZGQtNmUyZWY2MmQ1Y2ViXkEyXkFqcGdeQXVyMTI4MTk2NzMz._V1_FMjpg_UY480_.jpg",
          "stream_url": "https://aamir.ydc1wes.me/hls2/01/00005/7x4nw8piw1pp_,l,h,.urlset/master.m3u8?t=0gxMcACTKKhogIlja8BOBAa2y3ReDSKtyeOHsijzTh4&s=1778094994&e=21600&f=26015&i=0.0&sp=0",
          "headers": {
            "Referer": "https://speedostream1.com/"
          }
        },
        {
          "id": "X Class (2023) Season 1 Part 2 (VooVi Originals)",
          "title": "X Class (2023) Season 1 Part 2 (VooVi Originals)",
          "poster": "https://m.media-amazon.com/images/M/MV5BMGU2NDg5ODUtMmVhZS00MDBmLWEzMzctZWQzYTkxZTY3YWMxXkEyXkFqcGdeQXVyMTY5NTc5MTY2._V1_FMjpg_UY617_.jpg",
          "stream_url": "https://aamir.ydc1wes.me/hls2/01/00005/9js20pbepfg5_,l,h,.urlset/master.m3u8?t=Pw_fsKWpsSkn2eX_8ttf2YBQANb_TbdRooLJvkCVOy0&s=1778094995&e=21600&f=27443&i=0.0&sp=0",
          "headers": {
            "Referer": "https://speedostream1.com/"
          }
        },
        {
          "id": "X Class (2023) Season 1 Part 1 (VooVi Originals)",
          "title": "X Class (2023) Season 1 Part 1 (VooVi Originals)",
          "poster": "https://imego.lat/ib/I3ct1s3U1O.jpg",
          "stream_url": "https://aamir.ydc1wes.me/hls2/01/00005/jsp7jzv6s0bf_,l,h,.urlset/master.m3u8?t=QSlbqmMUHvzP-WaVdW1jyGwWHjIugV1d44RTFj7gutA&s=1778094995&e=21600&f=27231&i=0.0&sp=0",
          "headers": {
            "Referer": "https://speedostream1.com/"
          }
        },
        {
          "id": "Ek Phool Do Maali (2023) Season 1 Episode 2 (VooVi Originals)",
          "title": "Ek Phool Do Maali (2023) Season 1 Episode 2 (VooVi Originals)",
          "poster": "https://imego.lat/ib/jQtsxXslpq.jpg",
          "stream_url": "https://jnaove.ydc1wes.me/hls2/02/00005/3pncvj79amfy_,l,h,.urlset/master.m3u8?t=ta4XV_FopOAcvmhsL9a_159ZGVpoHDljRQ7LrZ314UQ&s=1778094996&e=21600&f=26835&i=0.0&sp=0",
          "headers": {
            "Referer": "https://speedostream1.com/"
          }
        },
        {
          "id": "Ek Phool Do Maali (2023) Season 1 Episode 1 (VooVi Originals)",
          "title": "Ek Phool Do Maali (2023) Season 1 Episode 1 (VooVi Originals)",
          "poster": "https://imego.lat/ib/jQtsxXslpq.jpg",
          "stream_url": "https://jnaove.ydc1wes.me/hls2/01/00005/vk98iy28azb4_,l,h,.urlset/master.m3u8?t=FAAlL0qArZN4OJQYKTdPzcqTyJSmCDzkohllzFWviJo&s=1778094996&e=21600&f=26834&i=0.0&sp=0",
          "headers": {
            "Referer": "https://speedostream1.com/"
          }
        },
        {
          "id": "Jaan Bujh Kar (2023) Season 2 Episode 1 (VooVi Originals)",
          "title": "Jaan Bujh Kar (2023) Season 2 Episode 1 (VooVi Originals)",
          "poster": "https://imego.lat/ib/HOUxguXBtO.jpg",
          "stream_url": "https://aamir.ydc1wes.me/hls2/01/00005/8zx1ijm4gl2z_,l,h,.urlset/master.m3u8?t=KG3HSQHQakKreu5uyVehlWsyYsijc-qO41XaRa3T7LQ&s=1778094997&e=21600&f=26505&i=0.0&sp=0",
          "headers": {
            "Referer": "https://speedostream1.com/"
          }
        },
        {
          "id": "Nehlee Par Dehla (2023) Season 1 Episode 3 (VooVi Originals)",
          "title": "Nehlee Par Dehla (2023) Season 1 Episode 3 (VooVi Originals)",
          "poster": "https://imego.lat/ib/ouOV2urX7D.jpg",
          "stream_url": "https://aamir.ydc1wes.me/hls2/01/00005/xep3lmlpfu40_,l,h,.urlset/master.m3u8?t=Q54pGdbKb49zNqL1Sp3rTRAeOC8TodPLPWBGT8FXepg&s=1778094998&e=21600&f=26016&i=0.0&sp=0",
          "headers": {
            "Referer": "https://speedostream1.com/"
          }
        },
        {
          "id": "Mona 69 (2023) Season 1 Episode 5 (VooVi Originals)",
          "title": "Mona 69 (2023) Season 1 Episode 5 (VooVi Originals)",
          "poster": "https://imego.lat/ib/xRn2h3zyS1.jpg",
          "stream_url": "https://jnaove.ydc1wes.me/hls2/01/00005/x0jv88gs4ti3_,l,h,.urlset/master.m3u8?t=agp-LUFucXPXEF-j_Nw6kPXZTmQbVjE4Tsg67n1UwgE&s=1778094998&e=21600&f=25795&i=0.0&sp=0",
          "headers": {
            "Referer": "https://speedostream1.com/"
          }
        },
        {
          "id": "Mona 69 (2023) Season 1 Episode 4 (VooVi Originals)",
          "title": "Mona 69 (2023) Season 1 Episode 4 (VooVi Originals)",
          "poster": "https://imego.lat/ib/xRn2h3zyS1.jpg",
          "stream_url": "https://jnaove.ydc1wes.me/hls2/01/00005/5zkl36jf5n97_,l,h,.urlset/master.m3u8?t=d0qwy3pHTC3ab81WL2JOKtyt-62N0tsqYbef3r5TY-0&s=1778094999&e=21600&f=25256&i=0.0&sp=0",
          "headers": {
            "Referer": "https://speedostream1.com/"
          }
        },
        {
          "id": "Nehlee Par Dehla (2023) Season 1 Episode 2 (VooVi Originals)",
          "title": "Nehlee Par Dehla (2023) Season 1 Episode 2 (VooVi Originals)",
          "poster": "https://imego.lat/ib/ouOV2urX7D.jpg",
          "stream_url": "https://aamir.ydc1wes.me/hls2/01/00005/5vicc1mfnghj_,l,h,.urlset/master.m3u8?t=ohpIuqsCDZNfWu34uOn85K_x8mYAJBPLyplUQ3apirc&s=1778094999&e=21600&f=25514&i=0.0&sp=0",
          "headers": {
            "Referer": "https://speedostream1.com/"
          }
        },
        {
          "id": "Nehlee Par Dehla (2023) Season 1 Episode 1 (VooVi Originals)",
          "title": "Nehlee Par Dehla (2023) Season 1 Episode 1 (VooVi Originals)",
          "poster": "https://imego.lat/ib/ouOV2urX7D.jpg",
          "stream_url": "https://aamir.ydc1wes.me/hls2/01/00005/fi2bo7s6gw93_,l,h,.urlset/master.m3u8?t=GrEOJAxS0Do72EqgBq0Ws3Ava6YCfL9Z8ZVj-oVE1pI&s=1778095000&e=21600&f=25515&i=0.0&sp=0",
          "headers": {
            "Referer": "https://speedostream1.com/"
          }
        },
        {
          "id": "Mona 69 (2023) Season 1 Episode 3 (VooVi Originals)",
          "title": "Mona 69 (2023) Season 1 Episode 3 (VooVi Originals)",
          "poster": "https://imego.lat/ib/ispRYG5hhy.jpg",
          "stream_url": "https://aamir.ydc1wes.me/hls2/01/00005/oyflczcxr6um_,l,h,.urlset/master.m3u8?t=FCGvQ7pK0pEsBwk2MEjqIkMXznITIu5TeYVgc6cJ7J0&s=1778095001&e=21600&f=25257&i=0.0&sp=0",
          "headers": {
            "Referer": "https://speedostream1.com/"
          }
        },
        {
          "id": "Mona 69 (2023) Season 1 Episode 2 (VooVi Originals)",
          "title": "Mona 69 (2023) Season 1 Episode 2 (VooVi Originals)",
          "poster": "https://imego.lat/ib/ispRYG5hhy.jpg",
          "stream_url": "https://aamir.ydc1wes.me/hls2/01/00005/ronyokzx7vxl_,l,h,.urlset/master.m3u8?t=XpA58BsfOsEm4YIUSlxZ0ShOUn0TOsUNPELa_eYz5ts&s=1778095001&e=21600&f=25020&i=0.0&sp=0",
          "headers": {
            "Referer": "https://speedostream1.com/"
          }
        },
        {
          "id": "Mona 69 (2023) Season 1 Episode 1 (VooVi Originals)",
          "title": "Mona 69 (2023) Season 1 Episode 1 (VooVi Originals)",
          "poster": "https://imego.lat/ib/ispRYG5hhy.jpg",
          "stream_url": "https://aamir.ydc1wes.me/hls2/01/00005/vzf2s7eoy9cf_,l,h,.urlset/master.m3u8?t=TCUzE9lfNcfSExme9kcZodIC1sVaOVnqqBJU41ECnNE&s=1778095003&e=21600&f=25019&i=0.0&sp=0",
          "headers": {
            "Referer": "https://speedostream1.com/"
          }
        },
        {
          "id": "Gulabo (2022) Season 1 Episode 7 (VooVi Originals)",
          "title": "Gulabo (2022) Season 1 Episode 7 (VooVi Originals)",
          "poster": "https://imego.lat/ib/R5LdVtmW8c.jpg",
          "stream_url": "https://aamir.ydc1wes.me/hls2/01/00004/a9nxozgtnxql_,l,h,.urlset/master.m3u8?t=gGSiEk27LJC48CaVXxDgfcVfbH9aQAf2Z_fzvOSZ514&s=1778095004&e=21600&f=20628&i=0.0&sp=0",
          "headers": {
            "Referer": "https://speedostream1.com/"
          }
        },
        {
          "id": "Mardana Sasur (2023) Season 2 Episode 3 (VooVi Originals)",
          "title": "Mardana Sasur (2023) Season 2 Episode 3 (VooVi Originals)",
          "poster": "https://imego.lat/ib/CGZsCctVBH.jpeg",
          "stream_url": "https://aamir.ydc1wes.me/hls2/01/00004/7wzthmh3c497_,l,h,.urlset/master.m3u8?t=5lH3Ro3pJFJhL9tQfeX4d-_pv2IbTsJ8Ssgp6cliOpM&s=1778095005&e=21600&f=24559&i=0.0&sp=0",
          "headers": {
            "Referer": "https://speedostream1.com/"
          }
        },
        {
          "id": "Pyar Idhar Udhar (2023) Season 1 Episode 3 (VooVi Originals)",
          "title": "Pyar Idhar Udhar (2023) Season 1 Episode 3 (VooVi Originals)",
          "poster": "https://imego.lat/ib/CsCQ1b4tyl.jpg",
          "stream_url": "https://jnaove.ydc1wes.me/hls2/02/00004/j242jiro0ves_,l,h,.urlset/master.m3u8?t=7XglmT77ZdDJ8jm5FQng5t0_LD1XF6X0_LRoBNeuvWY&s=1778095005&e=21600&f=24410&i=0.0&sp=0",
          "headers": {
            "Referer": "https://speedostream1.com/"
          }
        },
        {
          "id": "Mardana Sasur (2023) Season 2 Episode 2 (VooVi Originals)",
          "title": "Mardana Sasur (2023) Season 2 Episode 2 (VooVi Originals)",
          "poster": "https://imego.lat/ib/CGZsCctVBH.jpeg",
          "stream_url": "https://aamir.ydc1wes.me/hls2/01/00004/q08q4fqqt8bk_,l,h,.urlset/master.m3u8?t=h1_jJFi93O5XNlyqWighTb3VSw_99Dn78sbmUrZ2Mw4&s=1778095006&e=21600&f=24017&i=0.0&sp=0",
          "headers": {
            "Referer": "https://speedostream1.com/"
          }
        },
        {
          "id": "Pyar Idhar Udhar (2023) Season 1 Episode 2 (VooVi Originals)",
          "title": "Pyar Idhar Udhar (2023) Season 1 Episode 2 (VooVi Originals)",
          "poster": "https://imego.lat/ib/CsCQ1b4tyl.jpg",
          "stream_url": "https://jnaove.ydc1wes.me/hls2/02/00004/v4yeexo7ncwn_,l,h,.urlset/master.m3u8?t=HkwLTzlfKnG4PVzGGTuERlzHXxKlyfW7-Ux5V3mTAk8&s=1778095007&e=21600&f=24176&i=0.0&sp=0",
          "headers": {
            "Referer": "https://speedostream1.com/"
          }
        },
        {
          "id": "Mardana Sasur (2023) Season 2 Episode 1 (VooVi Originals)",
          "title": "Mardana Sasur (2023) Season 2 Episode 1 (VooVi Originals)",
          "poster": "https://imego.lat/ib/CGZsCctVBH.jpeg",
          "stream_url": "https://aamir.ydc1wes.me/hls2/01/00004/xgqhmyvzy7yf_,l,h,.urlset/master.m3u8?t=gXUyxKp6VMoU0hd1YF8P4JPCgCCCQ6gQLcbLvHL6MEY&s=1778095007&e=21600&f=24018&i=0.0&sp=0",
          "headers": {
            "Referer": "https://speedostream1.com/"
          }
        },
        {
          "id": "Pyar Idhar Udhar (2023) Season 1 Episode 1 (VooVi Originals)",
          "title": "Pyar Idhar Udhar (2023) Season 1 Episode 1 (VooVi Originals)",
          "poster": "https://imego.lat/ib/CsCQ1b4tyl.jpg",
          "stream_url": "https://aamir.ydc1wes.me/hls2/01/00004/yk2eo6mvo68e_,l,h,.urlset/master.m3u8?t=Oj4I9S7F6m2TSy8CGbV_9JvkLScp7pz9mDfg8Zxbiy8&s=1778095008&e=21600&f=23865&i=0.0&sp=0",
          "headers": {
            "Referer": "https://speedostream1.com/"
          }
        },
        {
          "id": "Seeti Maar Sajanwa (2023) Season 1 Episode 5 to 6 (VooVi Originals)",
          "title": "Seeti Maar Sajanwa (2023) Season 1 Episode 5 to 6 (VooVi Originals)",
          "poster": "https://imego.lat/ib/DsZ9Sg6lgA.jpeg",
          "stream_url": "https://aamir.ydc1wes.me/hls2/01/00004/1hspbwebms7n_,l,h,.urlset/master.m3u8?t=OHWk_jfnGWrAr-tcPCE2hp_uqiu1wP77_0eqq1X1BjY&s=1778095009&e=21600&f=23744&i=0.0&sp=0",
          "headers": {
            "Referer": "https://speedostream1.com/"
          }
        },
        {
          "id": "Seeti Maar Sajanwa (2023) Season 1 Episode 4 (VooVi Originals)",
          "title": "Seeti Maar Sajanwa (2023) Season 1 Episode 4 (VooVi Originals)",
          "poster": "https://imego.lat/ib/3uqXFNoYVd.png",
          "stream_url": "https://aamir.ydc1wes.me/hls2/01/00004/gdq9p4xthxw2_,l,h,.urlset/master.m3u8?t=oDnMzt-S7SMhEI4JhniKw3iAzH9GGVgoKVieO1kve2I&s=1778095009&e=21600&f=23562&i=0.0&sp=0",
          "headers": {
            "Referer": "https://speedostream1.com/"
          }
        },
        {
          "id": "Seeti Maar Sajanwa (2023) Season 1 Episode 2 (VooVi Originals)",
          "title": "Seeti Maar Sajanwa (2023) Season 1 Episode 2 (VooVi Originals)",
          "poster": "https://imego.lat/ib/KliBlNOASF.jpeg",
          "stream_url": "https://aamir.ydc1wes.me/hls2/01/00004/4y08mffl8r48_,l,h,.urlset/master.m3u8?t=ShuznSjYs3TbWP6LYOvGjjappXiqGcEcZ-Y95TzD7bY&s=1778095010&e=21600&f=23422&i=0.0&sp=0",
          "headers": {
            "Referer": "https://speedostream1.com/"
          }
        },
        {
          "id": "Seeti Maar Sajanwa (2023) Season 1 Episode 1 (VooVi Originals)",
          "title": "Seeti Maar Sajanwa (2023) Season 1 Episode 1 (VooVi Originals)",
          "poster": "https://imego.lat/ib/KliBlNOASF.jpeg",
          "stream_url": "https://aamir.ydc1wes.me/hls2/01/00004/mkw5bie1m309_,l,h,.urlset/master.m3u8?t=tGgr-t2r9vjjUQiYxMEYim_sJvG9KcETSVCFhHveLDI&s=1778095010&e=21600&f=23423&i=0.0&sp=0",
          "headers": {
            "Referer": "https://speedostream1.com/"
          }
        },
        {
          "id": "Rasili (2022) Season 1 Episode 6 (VooVi Originals)",
          "title": "Rasili (2022) Season 1 Episode 6 (VooVi Originals)",
          "poster": "https://imego.lat/ib/xjPmDuAKja.jpg",
          "stream_url": "https://aamir.ydc1wes.me/hls2/01/00004/xz0zu118bukf_,l,h,.urlset/master.m3u8?t=rBnZtBDZA3hF10TC9zqwCCJdVSF6LjyeIX7DG2d8GTU&s=1778095012&e=21600&f=23273&i=0.0&sp=0",
          "headers": {
            "Referer": "https://speedostream1.com/"
          }
        },
        {
          "id": "Mardana Sasur (2023) Season 1 Episode 6 (VooVi Originals)",
          "title": "Mardana Sasur (2023) Season 1 Episode 6 (VooVi Originals)",
          "poster": "https://imego.lat/ib/jLneFMeLqx.jpg",
          "stream_url": "https://aamir.ydc1wes.me/hls2/01/00004/q7j17yej0qgt_,l,h,.urlset/master.m3u8?t=rxZ5IzH_xi5gW1HgoOFkWzzsSVMHhawvSAhULRhD8Vc&s=1778095012&e=21600&f=21763&i=0.0&sp=0",
          "headers": {
            "Referer": "https://speedostream1.com/"
          }
        },
        {
          "id": "Psycho Saiyyan (2023) Season 1 Episode 6 (VooVi Originals)",
          "title": "Psycho Saiyyan (2023) Season 1 Episode 6 (VooVi Originals)",
          "poster": "https://imego.lat/ib/WPcRfd8g8y.jpg",
          "stream_url": "https://jnaove.ydc1wes.me/hls2/01/00004/k4ol7k4jgd81_,l,h,.urlset/master.m3u8?t=-e9ssY0vXzG2FZBcjCcDf4tF2wiJ-dthQQqb_utrEfw&s=1778095013&e=21600&f=22676&i=0.0&sp=0",
          "headers": {
            "Referer": "https://speedostream1.com/"
          }
        },
        {
          "id": "Psycho Saiyyan (2023) Season 1 Episode 5 (VooVi Originals)",
          "title": "Psycho Saiyyan (2023) Season 1 Episode 5 (VooVi Originals)",
          "poster": "https://imego.lat/ib/WPcRfd8g8y.jpg",
          "stream_url": "https://aamir.ydc1wes.me/hls2/01/00004/uwu82lfsr36d_,l,h,.urlset/master.m3u8?t=dcZhsroWous2E4ZT23-rMZGo6M9Mcj3rDyU6arl_U6g&s=1778095013&e=21600&f=22681&i=0.0&sp=0",
          "headers": {
            "Referer": "https://speedostream1.com/"
          }
        },
        {
          "id": "Psycho Saiyyan (2023) Season 1 Episode 4 (VooVi Originals)",
          "title": "Psycho Saiyyan (2023) Season 1 Episode 4 (VooVi Originals)",
          "poster": "https://imego.lat/ib/WPcRfd8g8y.jpg",
          "stream_url": "https://jnaove.ydc1wes.me/hls2/02/00004/43j7tw2qw9gb_,l,h,.urlset/master.m3u8?t=wD1p5UPcvtjiTRW6DATpffQHCR6RTuFIpB2rjYyo_qM&s=1778095014&e=21600&f=22685&i=0.0&sp=0",
          "headers": {
            "Referer": "https://speedostream1.com/"
          }
        },
        {
          "id": "Psycho Saiyyan (2023) Season 1 Episode 3 (VooVi Originals)",
          "title": "Psycho Saiyyan (2023) Season 1 Episode 3 (VooVi Originals)",
          "poster": "https://imego.lat/ib/yvsGl9lRck.jpg",
          "stream_url": "https://aamir.ydc1wes.me/hls2/01/00004/8bzz69wvduq8_,l,h,.urlset/master.m3u8?t=Y0fQaOulsYkrX_0ZD7OsyXWiQbN2lA04bpjZEN7UyiM&s=1778095015&e=21600&f=22498&i=0.0&sp=0",
          "headers": {
            "Referer": "https://speedostream1.com/"
          }
        },
        {
          "id": "Psycho Saiyyan (2023) Season 1 Episode 2 (VooVi Originals)",
          "title": "Psycho Saiyyan (2023) Season 1 Episode 2 (VooVi Originals)",
          "poster": "https://imego.lat/ib/WPcRfd8g8y.jpg",
          "stream_url": "https://aamir.ydc1wes.me/hls2/01/00004/0hji7xcnuq87_,l,h,.urlset/master.m3u8?t=5EBR4XUCatqnQgBFoZOKFqYe__vPSyglCDZ49WPio8g&s=1778095015&e=21600&f=22548&i=0.0&sp=0",
          "headers": {
            "Referer": "https://speedostream1.com/"
          }
        },
        {
          "id": "Gulabo (2022) Season 1 Episode 6 (VooVi Originals)",
          "title": "Gulabo (2022) Season 1 Episode 6 (VooVi Originals)",
          "poster": "https://imego.lat/ib/R5LdVtmW8c.jpg",
          "stream_url": "https://aamir.ydc1wes.me/hls2/01/00004/ueyscuflgrqg_,l,h,.urlset/master.m3u8?t=QvwxDcniTDATwNRl6ta-CdNrMQTQ61rt4tFN7j0odCA&s=1778095016&e=21600&f=20630&i=0.0&sp=0",
          "headers": {
            "Referer": "https://speedostream1.com/"
          }
        },
        {
          "id": "Psycho Saiyyan (2023) Season 1 Episode 1 (VooVi Originals)",
          "title": "Psycho Saiyyan (2023) Season 1 Episode 1 (VooVi Originals)",
          "poster": "https://imego.lat/ib/WPcRfd8g8y.jpg",
          "stream_url": "https://aamir.ydc1wes.me/hls2/01/00004/0vo26kuxnbrk_,l,h,.urlset/master.m3u8?t=3Rx1UW8GOuHXEmF-lW50-nD-7PPp05qjNB3bervPejU&s=1778095016&e=21600&f=22308&i=0.0&sp=0",
          "headers": {
            "Referer": "https://speedostream1.com/"
          }
        },
        {
          "id": "Kitab Ka Raaz (2023) Season 1 Episode 6 (VooVi Originals)",
          "title": "Kitab Ka Raaz (2023) Season 1 Episode 6 (VooVi Originals)",
          "poster": "https://imego.lat/ib/QzLNPtG8W3.jpeg",
          "stream_url": "https://aamir.ydc1wes.me/hls2/01/00004/3qbqdgilx8te_,l,h,.urlset/master.m3u8?t=4zkU4PIXbN6LDMDi4oBNxD6Q6ltyWlRtVjgnQ8bjCEg&s=1778095017&e=21600&f=22144&i=0.0&sp=0",
          "headers": {
            "Referer": "https://speedostream1.com/"
          }
        },
        {
          "id": "Kitab Ka Raaz (2023) Season 1 Episode 5 (VooVi Originals)",
          "title": "Kitab Ka Raaz (2023) Season 1 Episode 5 (VooVi Originals)",
          "poster": "https://imego.lat/ib/QzLNPtG8W3.jpeg",
          "stream_url": "https://aamir.ydc1wes.me/hls2/01/00004/3b4aa71v8nu9_,l,h,.urlset/master.m3u8?t=NacakbcupRokneN4ipwhQmhFeaNtt71LyR0b8Nr6OQo&s=1778095018&e=21600&f=22142&i=0.0&sp=0",
          "headers": {
            "Referer": "https://speedostream1.com/"
          }
        },
        {
          "id": "Mardana Sasur (2023) Season 1 Episode 5 (VooVi Originals)",
          "title": "Mardana Sasur (2023) Season 1 Episode 5 (VooVi Originals)",
          "poster": "https://imego.lat/ib/jLneFMeLqx.jpg",
          "stream_url": "https://aamir.ydc1wes.me/hls2/01/00004/7n32jpf68ag2_,l,h,.urlset/master.m3u8?t=qk9qdxGZgSDZRCFBo3Gb_rs8asc7HfWxMITK8fsE1-s&s=1778095018&e=21600&f=22102&i=0.0&sp=0",
          "headers": {
            "Referer": "https://speedostream1.com/"
          }
        },
        {
          "id": "Kitab Ka Raaz (2023) Season 1 Episode 3 (VooVi Originals)",
          "title": "Kitab Ka Raaz (2023) Season 1 Episode 3 (VooVi Originals)",
          "poster": "https://imego.lat/ib/QzLNPtG8W3.jpeg",
          "stream_url": "https://aamir.ydc1wes.me/hls2/01/00004/bquhgxxqt6fv_,l,h,.urlset/master.m3u8?t=lJlJWjXDlQI-iNBLNhS7ZZb2fJCdzyEvc4_pN_zWoMY&s=1778095019&e=21600&f=22009&i=0.0&sp=0",
          "headers": {
            "Referer": "https://speedostream1.com/"
          }
        },
        {
          "id": "Kitab Ka Raaz (2023) Season 1 (VooVi Originals)",
          "title": "Kitab Ka Raaz (2023) Season 1 (VooVi Originals)",
          "poster": "https://imego.lat/ib/QzLNPtG8W3.jpeg",
          "stream_url": "https://aamir.ydc1wes.me/hls2/01/00004/6rp5e3n05z0v_,l,h,.urlset/master.m3u8?t=q_mBBCCZAqf9Uu6h4nJXMNyWo40XqSTPnz9lDY5Nb-A&s=1778095020&e=21600&f=21862&i=0.0&sp=0",
          "headers": {
            "Referer": "https://speedostream1.com/"
          }
        },
        {
          "id": "Mardana Sasur (2023) Season 1 Episode 4 (VooVi Originals)",
          "title": "Mardana Sasur (2023) Season 1 Episode 4 (VooVi Originals)",
          "poster": "https://imego.lat/ib/jLneFMeLqx.jpg",
          "stream_url": "https://aamir.ydc1wes.me/hls2/01/00004/8o3673phq1ea_,l,h,.urlset/master.m3u8?t=hLntgqTnuSh-Ga8Ikxxc-iraJowl5X8n8z_-qg6OhTI&s=1778095020&e=21600&f=21629&i=0.0&sp=0",
          "headers": {
            "Referer": "https://speedostream1.com/"
          }
        },
        {
          "id": "Mardana Sasur (2023) Season 1 Episode 3 (VooVi Originals)",
          "title": "Mardana Sasur (2023) Season 1 Episode 3 (VooVi Originals)",
          "poster": "https://imego.lat/ib/jLneFMeLqx.jpg",
          "stream_url": "https://aamir.ydc1wes.me/hls2/01/00004/rklzqmaybki3_,l,h,.urlset/master.m3u8?t=UN-J-k7oJNK7imYkn-FX33YZkyHCEDraubA_yp1i0xg&s=1778095021&e=21600&f=21651&i=0.0&sp=0",
          "headers": {
            "Referer": "https://speedostream1.com/"
          }
        },
        {
          "id": "Mardana Sasur (2023) Season 1 Episode 2 (VooVi Originals)",
          "title": "Mardana Sasur (2023) Season 1 Episode 2 (VooVi Originals)",
          "poster": "https://imego.lat/ib/jLneFMeLqx.jpg",
          "stream_url": "https://aamir.ydc1wes.me/hls2/01/00004/0yut0wbs8b05_,l,h,.urlset/master.m3u8?t=oBGqlpsN6-m2nQSRhiX4aPlLLLORSQPsHy-4lPT6BBQ&s=1778095022&e=21600&f=21412&i=0.0&sp=0",
          "headers": {
            "Referer": "https://speedostream1.com/"
          }
        },
        {
          "id": "Mardana Sasur (2023) Season 1 Episode 1 (VooVi Originals)",
          "title": "Mardana Sasur (2023) Season 1 Episode 1 (VooVi Originals)",
          "poster": "https://imego.lat/ib/jLneFMeLqx.jpg",
          "stream_url": "https://aamir.ydc1wes.me/hls2/01/00004/l6vz0q8cz6qs_,l,h,.urlset/master.m3u8?t=BDzNnuF7FrxSdPmxXCKn_pr1--o1hERtNT8ztyf_srE&s=1778095022&e=21600&f=21411&i=0.0&sp=0",
          "headers": {
            "Referer": "https://speedostream1.com/"
          }
        },
        {
          "id": "Rasili (2022) Season 1 Episode 5 (VooVi Originals)",
          "title": "Rasili (2022) Season 1 Episode 5 (VooVi Originals)",
          "poster": "https://imego.lat/ib/xjPmDuAKja.jpg",
          "stream_url": "https://aamir.ydc1wes.me/hls2/01/00004/apjehh709aij_,l,h,.urlset/master.m3u8?t=YShjgz1wnqcn_uLJYB6F3WowwmA9BCHy1RE0yNBg_0k&s=1778095023&e=21600&f=21357&i=0.0&sp=0",
          "headers": {
            "Referer": "https://speedostream1.com/"
          }
        },
        {
          "id": "Gulabo (2022) Season 1 Episode 5 (VooVi Originals)",
          "title": "Gulabo (2022) Season 1 Episode 5 (VooVi Originals)",
          "poster": "https://imego.lat/ib/R5LdVtmW8c.jpg",
          "stream_url": "https://aamir.ydc1wes.me/hls2/01/00004/ee8navxv6dku_,l,h,.urlset/master.m3u8?t=R9OzJK6V8-RcTwC4o86UaMVlLZtakd3-UiOhfGKA4aU&s=1778095023&e=21600&f=20627&i=0.0&sp=0",
          "headers": {
            "Referer": "https://speedostream1.com/"
          }
        },
        {
          "id": "Rasili (2023) Season 1 Episode 4 (VooVi Originals)",
          "title": "Rasili (2023) Season 1 Episode 4 (VooVi Originals)",
          "poster": "https://imego.lat/ib/xjPmDuAKja.jpg",
          "stream_url": "https://aamir.ydc1wes.me/hls2/01/00004/r04h70expujq_,l,h,.urlset/master.m3u8?t=311vAYIJ_1PwmsnWjxorMzdlpY8fdFeS7BqA4LX_aag&s=1778095024&e=21600&f=20881&i=0.0&sp=0",
          "headers": {
            "Referer": "https://speedostream1.com/"
          }
        },
        {
          "id": "Rasili (2023) Season 1 Episode 3 (VooVi Originals)",
          "title": "Rasili (2023) Season 1 Episode 3 (VooVi Originals)",
          "poster": "https://imego.lat/ib/xjPmDuAKja.jpg",
          "stream_url": "https://aamir.ydc1wes.me/hls2/01/00004/uwq7ct033hm4_,l,h,.urlset/master.m3u8?t=SheJNOlkgRCblqA2WAVbJMI4f1K-KKUwO_qW2Z1Bvr0&s=1778095025&e=21600&f=20880&i=0.0&sp=0",
          "headers": {
            "Referer": "https://speedostream1.com/"
          }
        },
        {
          "id": "Rasili (2023) Season 1 Episode 2 (VooVi Originals)",
          "title": "Rasili (2023) Season 1 Episode 2 (VooVi Originals)",
          "poster": "https://imego.lat/ib/tIfEZqapdP.jpg",
          "stream_url": "https://aamir.ydc1wes.me/hls2/01/00004/0sjegpmjmx1y_,l,h,.urlset/master.m3u8?t=cC9QjuVLxy_6VVEhhu-6qrHFvLwsBhXoT9D97ndnA14&s=1778095025&e=21600&f=20729&i=0.0&sp=0",
          "headers": {
            "Referer": "https://speedostream1.com/"
          }
        },
        {
          "id": "Rasili (2023) Season 1 Episode 1 (VooVi Originals)",
          "title": "Rasili (2023) Season 1 Episode 1 (VooVi Originals)",
          "poster": "https://imego.lat/ib/tIfEZqapdP.jpg",
          "stream_url": "https://aamir.ydc1wes.me/hls2/01/00004/hwxupyyn6za8_,l,h,.urlset/master.m3u8?t=zThzXx5NwQ8I7oQnQ9tYKOmmzz73XoQ_aq2-oYxFmXs&s=1778095026&e=21600&f=20735&i=0.0&sp=0",
          "headers": {
            "Referer": "https://speedostream1.com/"
          }
        },
        {
          "id": "Gulabo (2022) Season 1 Episode 4 (VooVi Originals)",
          "title": "Gulabo (2022) Season 1 Episode 4 (VooVi Originals)",
          "poster": "https://imego.lat/ib/R5LdVtmW8c.jpg",
          "stream_url": "https://aamir.ydc1wes.me/hls2/01/00004/mzknp5nn4lbx_,l,h,.urlset/master.m3u8?t=gAZlbwkL-Mr6justYIRR9uTqA9zUWoDElU5UzHu54AU&s=1778095026&e=21600&f=20475&i=0.0&sp=0",
          "headers": {
            "Referer": "https://speedostream1.com/"
          }
        },
        {
          "id": "Gulabo (2022) Season 1 Episode 3 (VooVi Originals)",
          "title": "Gulabo (2022) Season 1 Episode 3 (VooVi Originals)",
          "poster": "https://imego.lat/ib/R5LdVtmW8c.jpg",
          "stream_url": "https://aamir.ydc1wes.me/hls2/01/00004/e1rwl6c0ge49_,l,h,.urlset/master.m3u8?t=-eMtiFJHKgMVA27VgJdGAIYNVoOnSAqXCnfJ3YVrmS0&s=1778095027&e=21600&f=20473&i=0.0&sp=0",
          "headers": {
            "Referer": "https://speedostream1.com/"
          }
        },
        {
          "id": "Gulabo (2022) Season 1 Episode 2 (VooVi Originals)",
          "title": "Gulabo (2022) Season 1 Episode 2 (VooVi Originals)",
          "poster": "https://imego.lat/ib/R5LdVtmW8c.jpg",
          "stream_url": "https://aamir.ydc1wes.me/hls2/01/00004/kllxv39s4mxr_,l,h,.urlset/master.m3u8?t=ASQBG4hOfvO7HF3IirBu9z4i8LqYetT5zg5BzsH21G0&s=1778095028&e=21600&f=21069&i=0.0&sp=0",
          "headers": {
            "Referer": "https://speedostream1.com/"
          }
        },
        {
          "id": "Gulabo (2022) Season 1 Episode 1 (VooVi Originals)",
          "title": "Gulabo (2022) Season 1 Episode 1 (VooVi Originals)",
          "poster": "https://imego.lat/ib/R5LdVtmW8c.jpg",
          "stream_url": "https://aamir.ydc1wes.me/hls2/01/00004/1ed8qng9q3z6_,l,h,.urlset/master.m3u8?t=KvWIIRxPUPFjZFSiuDZ1GQzThy7BP-NuCfaRYANxRPg&s=1778095029&e=21600&f=21070&i=0.0&sp=0",
          "headers": {
            "Referer": "https://speedostream1.com/"
          }
        },
        {
          "id": "ATM Bhabhi (2022) Season 1 Episode 8 (VooVi Originals)",
          "title": "ATM Bhabhi (2022) Season 1 Episode 8 (VooVi Originals)",
          "poster": "https://imego.lat/ib/oXqJu1Sxqq.jpeg",
          "stream_url": "https://aamir.ydc1wes.me/hls2/01/00004/4nbxjlig9bf2_,l,h,.urlset/master.m3u8?t=mcHu9Aqx7T_B1ztDr4cn7kHi1mqmVR9B6moEk8ORsoM&s=1778095030&e=21600&f=20101&i=0.0&sp=0",
          "headers": {
            "Referer": "https://speedostream1.com/"
          }
        },
        {
          "id": "ATM Bhabhi (2022) Season 1 Episode 7 (VooVi Originals)",
          "title": "ATM Bhabhi (2022) Season 1 Episode 7 (VooVi Originals)",
          "poster": "https://imego.lat/ib/oXqJu1Sxqq.jpeg",
          "stream_url": "https://aamir.ydc1wes.me/hls2/01/00004/ke6bsw7mpbqz_,l,h,.urlset/master.m3u8?t=Q2KWFRrwabLK5AxQnnv1yS-wVY0deAscEUEbC046TBw&s=1778095031&e=21600&f=20100&i=0.0&sp=0",
          "headers": {
            "Referer": "https://speedostream1.com/"
          }
        },
        {
          "id": "ATM Bhabhi (2022) Season 1 Episode 6 (VooVi Originals)",
          "title": "ATM Bhabhi (2022) Season 1 Episode 6 (VooVi Originals)",
          "poster": "https://imego.lat/ib/4joDDunR7d.jpg",
          "stream_url": "https://aamir.ydc1wes.me/hls2/01/00003/ka9ejyzg16bx_,l,h,.urlset/master.m3u8?t=qqvBSYdiheNtJBlu0u07UClLsIQ6ESO-07LDm3On6Ww&s=1778095031&e=21600&f=19984&i=0.0&sp=0",
          "headers": {
            "Referer": "https://speedostream1.com/"
          }
        },
        {
          "id": "ATM Bhabhi (2022) Season 1 Episode 5 (VooVi Originals)",
          "title": "ATM Bhabhi (2022) Season 1 Episode 5 (VooVi Originals)",
          "poster": "https://imego.lat/ib/4joDDunR7d.jpg",
          "stream_url": "https://aamir.ydc1wes.me/hls2/01/00003/xue6iex4ffnu_,l,h,.urlset/master.m3u8?t=Z_0iMHVCjrb7OcitQ75M_s03E5NgkjcUG8xFKfwwDLY&s=1778095032&e=21600&f=19985&i=0.0&sp=0",
          "headers": {
            "Referer": "https://speedostream1.com/"
          }
        },
        {
          "id": "Prem Game (2022) Season 1 Episode 4 (VooVi Originals)",
          "title": "Prem Game (2022) Season 1 Episode 4 (VooVi Originals)",
          "poster": "https://imego.lat/ib/ZJVFrNsqJ9.jpeg",
          "stream_url": "https://aamir.ydc1wes.me/hls2/01/00003/xuem7w26p4rr_,l,h,.urlset/master.m3u8?t=Y04JhIy2UULUsmi58GvjewZxwez_3O4fripIgZ9jgAU&s=1778095033&e=21600&f=19841&i=0.0&sp=0",
          "headers": {
            "Referer": "https://speedostream1.com/"
          }
        },
        {
          "id": "Prem Game (2022) Season 1 Episode 3 (VooVi Originals)",
          "title": "Prem Game (2022) Season 1 Episode 3 (VooVi Originals)",
          "poster": "https://imego.lat/ib/ZJVFrNsqJ9.jpeg",
          "stream_url": "https://aamir.ydc1wes.me/hls2/01/00003/8r5k4zmvszrd_,l,h,.urlset/master.m3u8?t=3VJLbee-6HbOTgUp-mZKYj53u1furPYRreAAF0cjSP4&s=1778095033&e=21600&f=19842&i=0.0&sp=0",
          "headers": {
            "Referer": "https://speedostream1.com/"
          }
        },
        {
          "id": "Prem Game (2022) Season 1 Episode 2 (VooVi Originals)",
          "title": "Prem Game (2022) Season 1 Episode 2 (VooVi Originals)",
          "poster": "https://imego.lat/ib/GRXDIFYj40.jpg",
          "stream_url": "https://aamir.ydc1wes.me/hls2/01/00003/4hziqmjrxsqv_,l,h,.urlset/master.m3u8?t=kQasdWwgacTJbtlZepRJAICMeQpQeG078pILPEFM-Lk&s=1778095034&e=21600&f=19697&i=0.0&sp=0",
          "headers": {
            "Referer": "https://speedostream1.com/"
          }
        },
        {
          "id": "ATM Bhabhi (2022) Season 1 Episode 4 (VooVi Originals)",
          "title": "ATM Bhabhi (2022) Season 1 Episode 4 (VooVi Originals)",
          "poster": "https://imego.lat/ib/4joDDunR7d.jpg",
          "stream_url": "https://aamir.ydc1wes.me/hls2/01/00003/t4n2qhik31ml_,l,h,.urlset/master.m3u8?t=0S6Ij_ahNS6P5CXwmUcWJCPnpKW6tbRtWLicDw5wJps&s=1778095035&e=21600&f=19503&i=0.0&sp=0",
          "headers": {
            "Referer": "https://speedostream1.com/"
          }
        },
        {
          "id": "Prem Game (2022) Season 1 Episode 1 (VooVi Originals)",
          "title": "Prem Game (2022) Season 1 Episode 1 (VooVi Originals)",
          "poster": "https://imego.lat/ib/GRXDIFYj40.jpg",
          "stream_url": "https://aamir.ydc1wes.me/hls2/01/00003/ki5h2hnqdubu_,l,h,.urlset/master.m3u8?t=aabvDP20kkyetEyKBGjKVDAMKyKAKVXaAEecnp4SoKE&s=1778095035&e=21600&f=19700&i=0.0&sp=0",
          "headers": {
            "Referer": "https://speedostream1.com/"
          }
        },
        {
          "id": "ATM Bhabhi (2022) Season 1 Episode 3 (VooVi Originals)",
          "title": "ATM Bhabhi (2022) Season 1 Episode 3 (VooVi Originals)",
          "poster": "https://imego.lat/ib/4joDDunR7d.jpg",
          "stream_url": "https://aamir.ydc1wes.me/hls2/01/00003/ptazklhgsqob_,l,h,.urlset/master.m3u8?t=qfdtolCue-A-IT6f0gITCV_nRj7cn_nLZlBvZ6PodIM&s=1778095036&e=21600&f=19500&i=0.0&sp=0",
          "headers": {
            "Referer": "https://speedostream1.com/"
          }
        },
        {
          "id": "Khuli Khidki (2022) Season 1 Episode 4 (VooVi Originals)",
          "title": "Khuli Khidki (2022) Season 1 Episode 4 (VooVi Originals)",
          "poster": "https://imego.lat/ib/UPtCRtszyT.jpg",
          "stream_url": "https://aamir.ydc1wes.me/hls2/01/00003/pow0shfkxplh_,l,h,.urlset/master.m3u8?t=4xpTwZptIjZ2xk-EhPximzgGoOk_Z9d4kyNf_diDYb8&s=1778095037&e=21600&f=19327&i=0.0&sp=0",
          "headers": {
            "Referer": "https://speedostream1.com/"
          }
        },
        {
          "id": "ATM Bhabhi (2022) Season 1 Episode 2 (VooVi Originals)",
          "title": "ATM Bhabhi (2022) Season 1 Episode 2 (VooVi Originals)",
          "poster": "https://imego.lat/ib/4joDDunR7d.jpg",
          "stream_url": "https://aamir.ydc1wes.me/hls2/01/00003/98htcqx6clip_,l,h,.urlset/master.m3u8?t=6S9hU52eLL1MOZovjGggZO9Nb1cIWZVvbVCZfz53MxU&s=1778095038&e=21600&f=19390&i=0.0&sp=0",
          "headers": {
            "Referer": "https://speedostream1.com/"
          }
        },
        {
          "id": "ATM Bhabhi (2022) Season 1 Episode 1 (VooVi Originals)",
          "title": "ATM Bhabhi (2022) Season 1 Episode 1 (VooVi Originals)",
          "poster": "https://imego.lat/ib/4joDDunR7d.jpg",
          "stream_url": "https://aamir.ydc1wes.me/hls2/01/00003/50tlxzoa054t_,l,h,.urlset/master.m3u8?t=9Xa8zTnbmJgivZ95cpbsAVRIqRr7mCCuT0LhEeKKKnU&s=1778095038&e=21600&f=19391&i=0.0&sp=0",
          "headers": {
            "Referer": "https://speedostream1.com/"
          }
        },
        {
          "id": "Khuli Khidki (2022) Season 1 Episode 3 (VooVi Originals)",
          "title": "Khuli Khidki (2022) Season 1 Episode 3 (VooVi Originals)",
          "poster": "https://imego.lat/ib/UPtCRtszyT.jpg",
          "stream_url": "https://aamir.ydc1wes.me/hls2/01/00003/1elkcm4b6dh7_,l,h,.urlset/master.m3u8?t=DG1cluyY6Psw3ywdo0x6bejljkY1dDOt699R4ni-6bo&s=1778095039&e=21600&f=19326&i=0.0&sp=0",
          "headers": {
            "Referer": "https://speedostream1.com/"
          }
        },
        {
          "id": "Khuli Khidki (2022) Season 1 Episode 1 (VooVi Originals)",
          "title": "Khuli Khidki (2022) Season 1 Episode 1 (VooVi Originals)",
          "poster": "https://imego.lat/ib/UPtCRtszyT.jpg",
          "stream_url": "https://aamir.ydc1wes.me/hls2/01/00003/9tvjhzbhrp3g_,l,h,.urlset/master.m3u8?t=K-Y_93c3dXb7kXSAhR_IvW4nEDrqcMEyPua5lOZHh3w&s=1778095039&e=21600&f=19184&i=0.0&sp=0",
          "headers": {
            "Referer": "https://speedostream1.com/"
          }
        },
        {
          "id": "Khuli Khidki (2022) Season 1 Episode 2 (VooVi Originals)",
          "title": "Khuli Khidki (2022) Season 1 Episode 2 (VooVi Originals)",
          "poster": "https://imego.lat/ib/UPtCRtszyT.jpg",
          "stream_url": "https://aamir.ydc1wes.me/hls2/01/00003/tfn51ztkcciu_,l,h,.urlset/master.m3u8?t=gvcUt2Tr0MJ0eXmff_R20xWFHmRWFtnDNgVDhWpf-84&s=1778095041&e=21600&f=19185&i=0.0&sp=0",
          "headers": {
            "Referer": "https://speedostream1.com/"
          }
        },
        {
          "id": "Jaan Bujh Kar (2022) Season 1 Episode 4 (VooVi Originals)",
          "title": "Jaan Bujh Kar (2022) Season 1 Episode 4 (VooVi Originals)",
          "poster": "https://imego.lat/ib/hMjWxuTrQ0.jpg",
          "stream_url": "https://aamir.ydc1wes.me/hls2/01/00003/576miwj7m6dw_,l,h,.urlset/master.m3u8?t=tb3YlIAh5CVtyiK7OplISEhZ9-hjftpnxFXmnrl1np0&s=1778095041&e=21600&f=18803&i=0.0&sp=0",
          "headers": {
            "Referer": "https://speedostream1.com/"
          }
        },
        {
          "id": "Jaan Bujh Kar (2022) Season 1 Episode 3 (VooVi Originals)",
          "title": "Jaan Bujh Kar (2022) Season 1 Episode 3 (VooVi Originals)",
          "poster": "https://imego.lat/ib/hMjWxuTrQ0.jpg",
          "stream_url": "https://aamir.ydc1wes.me/hls2/01/00003/5k4h5wtdqpja_,l,h,.urlset/master.m3u8?t=HoDIfER4sPsdZJJ4eLgWWjw779lMeYbmxr6hAk344x0&s=1778095042&e=21600&f=18802&i=0.0&sp=0",
          "headers": {
            "Referer": "https://speedostream1.com/"
          }
        },
        {
          "id": "Jaan Bujh Kar (2022) Season 1 Episode 1 (VooVi Originals)",
          "title": "Jaan Bujh Kar (2022) Season 1 Episode 1 (VooVi Originals)",
          "poster": "https://imego.lat/ib/hMjWxuTrQ0.jpg",
          "stream_url": "https://aamir.ydc1wes.me/hls2/01/00003/fmvhwzjr5jhy_,l,h,.urlset/master.m3u8?t=DEnMLOYSlbugrIQUEdzguvwZAxh8ozWMkwI2OSU1qCY&s=1778095043&e=21600&f=18266&i=0.0&sp=0",
          "headers": {
            "Referer": "https://speedostream1.com/"
          }
        },
        {
          "id": "Dildo (2022) Season 1 Episode 5 (VooVi Originals)",
          "title": "Dildo (2022) Season 1 Episode 5 (VooVi Originals)",
          "poster": "https://imego.lat/ib/NtsLrAcE4K.jpg",
          "stream_url": "https://aamir.ydc1wes.me/hls2/01/00003/08dhzjg78h3n_,l,o,.urlset/master.m3u8?t=_p4DG-lLvC6DWq1YwrY2Ck_sF726nnE4kHN3YVGPtLM&s=1778095044&e=21600&f=17246&i=0.0&sp=0",
          "headers": {
            "Referer": "https://speedostream1.com/"
          }
        },
        {
          "id": "Dildo (2022) Season 1 Episode 4 (VooVi Originals)",
          "title": "Dildo (2022) Season 1 Episode 4 (VooVi Originals)",
          "poster": "https://imego.lat/ib/NtsLrAcE4K.jpg",
          "stream_url": "https://aamir.ydc1wes.me/hls2/01/00003/ntqt5hcs7t1a_,l,o,.urlset/master.m3u8?t=Yqqp8U7tBCMpPVxZKCaXJ_E_rv6RDq47N8TaT7pJT2s&s=1778095044&e=21600&f=17244&i=0.0&sp=0",
          "headers": {
            "Referer": "https://speedostream1.com/"
          }
        },
        {
          "id": "Dildo (2022) Season 1 Episode 3 (VooVi Originals)",
          "title": "Dildo (2022) Season 1 Episode 3 (VooVi Originals)",
          "poster": "https://imego.lat/ib/NtsLrAcE4K.jpg",
          "stream_url": "https://aamir.ydc1wes.me/hls2/01/00003/raxhlx3vmgfu_,l,o,.urlset/master.m3u8?t=RWbweW9w6GEiuLOR5wlrLrCvSG1ms5_X6uHX5B-YmzY&s=1778095045&e=21600&f=17243&i=0.0&sp=0",
          "headers": {
            "Referer": "https://speedostream1.com/"
          }
        },
        {
          "id": "Dildo (2022) Season 1 Episode 2 (VooVi Originals)",
          "title": "Dildo (2022) Season 1 Episode 2 (VooVi Originals)",
          "poster": "https://imego.lat/ib/NtsLrAcE4K.jpg",
          "stream_url": "https://aamir.ydc1wes.me/hls2/01/00003/k0gbn1c0nbgm_,l,o,.urlset/master.m3u8?t=CGicKUqFHjg9_02jQqIZ-2ZSSl8DQ5MaSWuVXgr2XHQ&s=1778095046&e=21600&f=17112&i=0.0&sp=0",
          "headers": {
            "Referer": "https://speedostream1.com/"
          }
        },
        {
          "id": "Dildo (2022) Season 1 Episode 1 (VooVi Originals)",
          "title": "Dildo (2022) Season 1 Episode 1 (VooVi Originals)",
          "poster": "https://imego.lat/ib/NtsLrAcE4K.jpg",
          "stream_url": "https://aamir.ydc1wes.me/hls2/01/00003/jtcg20a10seq_,l,o,.urlset/master.m3u8?t=9ouoqYtz-F-jcZ_KYcUyIm-jlhyKu0jx16fmu3NrXbI&s=1778095046&e=21600&f=17110&i=0.0&sp=0",
          "headers": {
            "Referer": "https://speedostream1.com/"
          }
        },
        {
          "id": "Rangili Ragini (2022) Season 1 Episode 4 (VooVi Originals)",
          "title": "Rangili Ragini (2022) Season 1 Episode 4 (VooVi Originals)",
          "poster": "https://imego.lat/ib/rUgbR7kD6d.jpg",
          "stream_url": "https://aamir.ydc1wes.me/hls2/01/00003/8ig19u9fqaa4_,l,o,.urlset/master.m3u8?t=QhinuV8QYXmbFrIxZqhbNbEKw0-gnZNY8bTJlTrrKOQ&s=1778095047&e=21600&f=16912&i=0.0&sp=0",
          "headers": {
            "Referer": "https://speedostream1.com/"
          }
        },
        {
          "id": "Rangili Ragini (2022) Season 1 Episode 3 VooVi Originals",
          "title": "Rangili Ragini (2022) Season 1 Episode 3 VooVi Originals",
          "poster": "https://imego.lat/ib/rUgbR7kD6d.jpg",
          "stream_url": "https://aamir.ydc1wes.me/hls2/01/00003/qpdwyvw3291l_,l,o,.urlset/master.m3u8?t=omC0cD7RbD74qcV2lmXa2fJ3nZFPAhPBT7-iqYZsNW8&s=1778095047&e=21600&f=16911&i=0.0&sp=0",
          "headers": {
            "Referer": "https://speedostream1.com/"
          }
        },
        {
          "id": "Chaar Saheliyan (2022) Season 1 Episode 2 VooVi Originals",
          "title": "Chaar Saheliyan (2022) Season 1 Episode 2 VooVi Originals",
          "poster": "https://imego.lat/ib/veqijCeDyd.jpg",
          "stream_url": "https://aamir.ydc1wes.me/hls2/01/00003/kbw45ig9ucj1_,l,o,.urlset/master.m3u8?t=I46YDrr8xAAXK8E6KOZLIRXEPuL5xV-fbKy97D0fxjw&s=1778095048&e=21600&f=16692&i=0.0&sp=0",
          "headers": {
            "Referer": "https://speedostream1.com/"
          }
        },
        {
          "id": "Chaar Saheliyan (2022) Season 1 Episode 1 VooVi Originals",
          "title": "Chaar Saheliyan (2022) Season 1 Episode 1 VooVi Originals",
          "poster": "https://imego.lat/ib/veqijCeDyd.jpg",
          "stream_url": "https://aamir.ydc1wes.me/hls2/01/00003/0mb5jjp0zegy_,l,o,.urlset/master.m3u8?t=Duf2wlRHjBUsGYobkbJC1KK5U9TztpCwDuKH7RxsxPw&s=1778095049&e=21600&f=16691&i=0.0&sp=0",
          "headers": {
            "Referer": "https://speedostream1.com/"
          }
        },
        {
          "id": "Rangili Ragini (2022) Season 1 Episode 2 VooVi Originals",
          "title": "Rangili Ragini (2022) Season 1 Episode 2 VooVi Originals",
          "poster": "https://imego.lat/ib/heclO78pnZ.jpg",
          "stream_url": "https://aamir.ydc1wes.me/hls2/01/00003/hc8bag22mmh6_,l,o,.urlset/master.m3u8?t=_oSBCaXzoHWs8oykvEVvt7AU50HeO-pkwcbIoAY9oAE&s=1778095050&e=21600&f=16576&i=0.0&sp=0",
          "headers": {
            "Referer": "https://speedostream1.com/"
          }
        },
        {
          "id": "Rangili Ragini (2022) Season 1 Episode 1 VooVi Originals",
          "title": "Rangili Ragini (2022) Season 1 Episode 1 VooVi Originals",
          "poster": "https://imego.lat/ib/heclO78pnZ.jpg",
          "stream_url": "https://aamir.ydc1wes.me/hls2/01/00003/a9ihj5j2ru4y_,l,o,.urlset/master.m3u8?t=Z2kYJZfA09Fy-t6PNVL_8dHrn8UO-d1hYloTxjgBHg8&s=1778095050&e=21600&f=16581&i=0.0&sp=0",
          "headers": {
            "Referer": "https://speedostream1.com/"
          }
        }
      ]
    }
  ]
}